{
"Version": "8.7.4","Activities": [
{"Timestamp": "2020-10-30 14:48:52", "File": "Energy%203D%20ENGT%20180%20Design%20PROJECT.ng3", "Camera": {"Position": {"x": 51.428, "y": -83.793, "z": 24.371}, "Direction": {"x": -0.467, "y": 0.876, "z": -0.12}, "Mode": "Rotate"}},
{"Timestamp": "2020-10-30 14:48:56", "File": "Energy%203D%20ENGT%20180%20Design%20PROJECT.ng3", "Camera": {"Position": {"x": -37.814, "y": -77.466, "z": 55.47}, "Direction": {"x": 0.399, "y": 0.815, "z": -0.421}, "Mode": "Rotate"}},
{"Timestamp": "2020-10-30 14:49:16", "File": "Energy%203D%20ENGT%20180%20Design%20PROJECT.ng3", "Camera": {"Position": {"x": -43.24, "y": -78.627, "z": 46.892}, "Direction": {"x": 0.451, "y": 0.826, "z": -0.338}, "Mode": "Rotate"}},
{"Timestamp": "2020-10-30 14:49:17", "File": "Energy%203D%20ENGT%20180%20Design%20PROJECT.ng3", "Camera": {"Position": {"x": 81.924, "y": -57.209, "z": 31.499}, "Direction": {"x": -0.763, "y": 0.618, "z": -0.189}, "Mode": "Rotate"}},
{"Timestamp": "2020-10-30 14:49:18", "File": "Energy%203D%20ENGT%20180%20Design%20PROJECT.ng3", "Camera": {"Position": {"x": 82.557, "y": -56.419, "z": 31.499}, "Direction": {"x": -0.769, "y": 0.61, "z": -0.189}, "Mode": "Rotate"}},
{"Timestamp": "2020-10-30 14:49:22", "File": "Energy%203D%20ENGT%20180%20Design%20PROJECT.ng3", "Camera": {"Position": {"x": 46.704, "y": -86.975, "z": 11.516}, "Direction": {"x": -0.421, "y": 0.907, "z": 0.005}, "Mode": "Rotate"}},
{"Timestamp": "2020-10-30 14:49:29", "File": "Energy%203D%20ENGT%20180%20Design%20PROJECT.ng3", "Camera": {"Position": {"x": 68.305, "y": -69.936, "z": 35.531}, "Direction": {"x": -0.631, "y": 0.742, "z": -0.228}, "Mode": "Rotate"}},
{"Timestamp": "2020-10-30 14:49:31", "File": "Energy%203D%20ENGT%20180%20Design%20PROJECT.ng3", "Camera": {"Position": {"x": 102.006, "y": -8.501, "z": 37.534}, "Direction": {"x": -0.958, "y": 0.146, "z": -0.247}, "Mode": "Rotate"}},
{"Timestamp": "2020-10-30 14:55:45", "File": "Energy%203D%20ENGT%20180%20Design%20PROJECT.ng3", "Camera": {"Position": {"x": -20.7, "y": -81.114, "z": 61.009}, "Direction": {"x": 0.226, "y": 0.848, "z": -0.479}, "Mode": "Rotate"}},
{"Timestamp": "2020-10-30 14:55:50", "File": "Energy%203D%20ENGT%20180%20Design%20PROJECT.ng3", "Camera": {"Position": {"x": 51.175, "y": -82.976, "z": 33.248}, "Direction": {"x": -0.451, "y": 0.866, "z": -0.218}, "Mode": "Rotate"}},
{"Timestamp": "2020-10-30 14:55:52", "File": "Energy%203D%20ENGT%20180%20Design%20PROJECT.ng3", "Camera": {"Position": {"x": 51.635, "y": -82.736, "z": 33.248}, "Direction": {"x": -0.455, "y": 0.863, "z": -0.218}, "Mode": "Rotate"}},
{"Timestamp": "2020-10-30 14:55:57", "File": "Energy%203D%20ENGT%20180%20Design%20PROJECT.ng3", "Camera": {"Position": {"x": 52.093, "y": -82.493, "z": 33.248}, "Direction": {"x": -0.459, "y": 0.861, "z": -0.218}, "Mode": "Rotate"}},
{"Timestamp": "2020-10-30 14:55:57", "File": "Energy%203D%20ENGT%20180%20Design%20PROJECT.ng3", "Camera": {"Position": {"x": 52.55, "y": -82.247, "z": 33.248}, "Direction": {"x": -0.464, "y": 0.859, "z": -0.218}, "Mode": "Rotate"}},
{"Timestamp": "2020-10-30 14:56:02", "File": "Energy%203D%20ENGT%20180%20Design%20PROJECT.ng3", "Change City": {"Old City": "Boston, MA", "New City": "Ilheus, Brazil"}},
{"Timestamp": "2020-10-30 14:56:11", "File": "Energy%203D%20ENGT%20180%20Design%20PROJECT.ng3", "Camera": {"Position": {"x": 54, "y": -80.598, "z": 36.349}, "Direction": {"x": -0.477, "y": 0.843, "z": -0.247}, "Mode": "Rotate"}},
{"Timestamp": "2020-10-30 14:56:34", "File": "Energy%203D%20ENGT%20180%20Design%20PROJECT.ng3", "Camera": {"Position": {"x": 15.31, "y": 113.72, "z": 25.411}, "Direction": {"x": -0.11, "y": -0.983, "z": -0.144}, "Mode": "Rotate"}},
{"Timestamp": "2020-10-30 14:56:36", "File": "Energy%203D%20ENGT%20180%20Design%20PROJECT.ng3", "Edit Window": {"Type": "Window", "Building": 2, "ID": 19, "Coordinates": [{"x": 29, "y": 25, "z": 15}, {"x": 29, "y": 25, "z": 7}, {"x": 17, "y": 25, "z": 15}, {"x": 17, "y": 25, "z": 7}]}},
{"Timestamp": "2020-10-30 14:56:36", "File": "Energy%203D%20ENGT%20180%20Design%20PROJECT.ng3", "Camera": {"Position": {"x": 13.211, "y": 113.855, "z": 25.937}, "Direction": {"x": -0.09, "y": -0.985, "z": -0.149}, "Mode": "Rotate"}},
{"Timestamp": "2020-10-30 14:56:38", "File": "Energy%203D%20ENGT%20180%20Design%20PROJECT.ng3", "Camera": {"Position": {"x": 12.687, "y": 113.902, "z": 25.937}, "Direction": {"x": -0.086, "y": -0.985, "z": -0.149}, "Mode": "Rotate"}},
{"Timestamp": "2020-10-30 14:56:42", "File": "Energy%203D%20ENGT%20180%20Design%20PROJECT.ng3", "Edit Window": {"Type": "Window", "Building": 2, "ID": 19, "Coordinates": [{"x": 29, "y": 25, "z": 15}, {"x": 29, "y": 25, "z": 7}, {"x": 11, "y": 25, "z": 15}, {"x": 11, "y": 25, "z": 7}]}},
{"Timestamp": "2020-10-30 14:56:44", "File": "Energy%203D%20ENGT%20180%20Design%20PROJECT.ng3", "Camera": {"Position": {"x": 55.944, "y": -83.287, "z": 8.991}, "Direction": {"x": -0.493, "y": 0.87, "z": 0.01}, "Mode": "Rotate"}},
{"Timestamp": "2020-10-30 14:56:46", "File": "Energy%203D%20ENGT%20180%20Design%20PROJECT.ng3", "Camera": {"Position": {"x": -9.073, "y": -95.886, "z": 19.606}, "Direction": {"x": 0.119, "y": 0.989, "z": -0.09}, "Mode": "Rotate"}},
{"Timestamp": "2020-10-30 14:56:47", "File": "Energy%203D%20ENGT%20180%20Design%20PROJECT.ng3", "Camera": {"Position": {"x": -8.542, "y": -95.9, "z": 20.136}, "Direction": {"x": 0.114, "y": 0.989, "z": -0.095}, "Mode": "Rotate"}},
{"Timestamp": "2020-10-30 14:56:50", "File": "Energy%203D%20ENGT%20180%20Design%20PROJECT.ng3", "Edit Window": {"Type": "Window", "Building": 2, "ID": 14, "Coordinates": [{"x": -20, "y": -25, "z": 15}, {"x": -20, "y": -25, "z": 5}, {"x": -12, "y": -25, "z": 15}, {"x": -12, "y": -25, "z": 5}]}},
{"Timestamp": "2020-10-30 14:56:50", "File": "Energy%203D%20ENGT%20180%20Design%20PROJECT.ng3", "Camera": {"Position": {"x": -5.384, "y": -96.216, "z": 20.136}, "Direction": {"x": 0.085, "y": 0.992, "z": -0.095}, "Mode": "Rotate"}},
{"Timestamp": "2020-10-30 14:56:53", "File": "Energy%203D%20ENGT%20180%20Design%20PROJECT.ng3", "Edit Window": {"Type": "Window", "Building": 2, "ID": 15, "Coordinates": [{"x": 14, "y": -25, "z": 15}, {"x": 14, "y": -25, "z": 5}, {"x": 22, "y": -25, "z": 15}, {"x": 22, "y": -25, "z": 5}]}},
{"Timestamp": "2020-10-30 14:56:53", "File": "Energy%203D%20ENGT%20180%20Design%20PROJECT.ng3", "Camera": {"Position": {"x": -4.857, "y": -96.26, "z": 20.136}, "Direction": {"x": 0.08, "y": 0.992, "z": -0.095}, "Mode": "Rotate"}},
{"Timestamp": "2020-10-30 14:56:58", "File": "Energy%203D%20ENGT%20180%20Design%20PROJECT.ng3", "Add Window": {"Type": "Window", "Building": 2, "ID": 33, "Coordinates": [{"x": 6, "y": -25, "z": 13}, {"x": 6, "y": -25, "z": 5}, {"x": 10, "y": -25, "z": 13}, {"x": 10, "y": -25, "z": 5}]}},
{"Timestamp": "2020-10-30 14:57:04", "File": "Energy%203D%20ENGT%20180%20Design%20PROJECT.ng3", "Add Window": {"Type": "Window", "Building": 2, "ID": 34, "Coordinates": [{"x": -4, "y": -25, "z": 13}, {"x": -4, "y": -25, "z": 5}, {"x": -8, "y": -25, "z": 13}, {"x": -8, "y": -25, "z": 5}]}},
{"Timestamp": "2020-10-30 14:57:05", "File": "Energy%203D%20ENGT%20180%20Design%20PROJECT.ng3", "Camera": {"Position": {"x": -4.853, "y": -96.209, "z": 20.664}, "Direction": {"x": 0.08, "y": 0.992, "z": -0.1}, "Mode": "Rotate"}},
{"Timestamp": "2020-10-30 14:57:20", "File": "Energy%203D%20ENGT%20180%20Design%20PROJECT.ng3", "BuildingCost": {"Foundation": 2, "Amount": 218690.09360535626}},
{"Timestamp": "2020-10-30 14:57:22", "File": "Energy%203D%20ENGT%20180%20Design%20PROJECT.ng3", "Camera": {"Position": {"x": -5.379, "y": -96.165, "z": 20.664}, "Direction": {"x": 0.084, "y": 0.991, "z": -0.1}, "Mode": "Rotate"}},
{"Timestamp": "2020-10-30 14:57:25", "File": "Energy%203D%20ENGT%20180%20Design%20PROJECT.ng3", "Remove Window": {"Type": "Window", "Building": 2, "ID": 34, "Coordinates": [{"x": -4, "y": -25, "z": 13}, {"x": -4, "y": -25, "z": 5}, {"x": -8, "y": -25, "z": 13}, {"x": -8, "y": -25, "z": 5}]}},
{"Timestamp": "2020-10-30 14:57:26", "File": "Energy%203D%20ENGT%20180%20Design%20PROJECT.ng3", "Remove Window": {"Type": "Window", "Building": 2, "ID": 33, "Coordinates": [{"x": 6, "y": -25, "z": 13}, {"x": 6, "y": -25, "z": 5}, {"x": 10, "y": -25, "z": 13}, {"x": 10, "y": -25, "z": 5}]}},
{"Timestamp": "2020-10-30 14:57:29", "File": "Energy%203D%20ENGT%20180%20Design%20PROJECT.ng3", "Edit Window": {"Type": "Window", "Building": 2, "ID": 14, "Coordinates": [{"x": -16, "y": -25, "z": 15}, {"x": -16, "y": -25, "z": 5}, {"x": -8, "y": -25, "z": 15}, {"x": -8, "y": -25, "z": 5}]}},
{"Timestamp": "2020-10-30 14:57:31", "File": "Energy%203D%20ENGT%20180%20Design%20PROJECT.ng3", "Edit Window": {"Type": "Window", "Building": 2, "ID": 14, "Coordinates": [{"x": -16, "y": -25, "z": 15}, {"x": -16, "y": -25, "z": 5}, {"x": -10, "y": -25, "z": 15}, {"x": -10, "y": -25, "z": 5}]}},
{"Timestamp": "2020-10-30 14:57:31", "File": "Energy%203D%20ENGT%20180%20Design%20PROJECT.ng3", "Camera": {"Position": {"x": -4.853, "y": -96.209, "z": 20.664}, "Direction": {"x": 0.08, "y": 0.992, "z": -0.1}, "Mode": "Rotate"}},
{"Timestamp": "2020-10-30 14:57:33", "File": "Energy%203D%20ENGT%20180%20Design%20PROJECT.ng3", "Edit Window": {"Type": "Window", "Building": 2, "ID": 13, "Coordinates": [{"x": -28, "y": -25, "z": 15}, {"x": -28, "y": -25, "z": 5}, {"x": -22, "y": -25, "z": 15}, {"x": -22, "y": -25, "z": 5}]}},
{"Timestamp": "2020-10-30 14:57:37", "File": "Energy%203D%20ENGT%20180%20Design%20PROJECT.ng3", "Edit Window": {"Type": "Window", "Building": 2, "ID": 15, "Coordinates": [{"x": 14, "y": -25, "z": 15}, {"x": 14, "y": -25, "z": 5}, {"x": 20, "y": -25, "z": 15}, {"x": 20, "y": -25, "z": 5}]}},
{"Timestamp": "2020-10-30 14:57:37", "File": "Energy%203D%20ENGT%20180%20Design%20PROJECT.ng3", "Camera": {"Position": {"x": -3.794, "y": -96.234, "z": 21.193}, "Direction": {"x": 0.07, "y": 0.992, "z": -0.105}, "Mode": "Rotate"}},
{"Timestamp": "2020-10-30 14:57:38", "File": "Energy%203D%20ENGT%20180%20Design%20PROJECT.ng3", "Camera": {"Position": {"x": -3.79, "y": -96.177, "z": 21.721}, "Direction": {"x": 0.07, "y": 0.992, "z": -0.11}, "Mode": "Rotate"}},
{"Timestamp": "2020-10-30 14:57:39", "File": "Energy%203D%20ENGT%20180%20Design%20PROJECT.ng3", "Edit Window": {"Type": "Window", "Building": 2, "ID": 16, "Coordinates": [{"x": 26, "y": -25, "z": 15}, {"x": 26, "y": -25, "z": 5}, {"x": 32, "y": -25, "z": 15}, {"x": 32, "y": -25, "z": 5}]}},
{"Timestamp": "2020-10-30 14:57:40", "File": "Energy%203D%20ENGT%20180%20Design%20PROJECT.ng3", "Camera": {"Position": {"x": -3.794, "y": -96.234, "z": 21.193}, "Direction": {"x": 0.07, "y": 0.992, "z": -0.105}, "Mode": "Rotate"}},
{"Timestamp": "2020-10-30 14:57:43", "File": "Energy%203D%20ENGT%20180%20Design%20PROJECT.ng3", "Edit Window": {"Type": "Window", "Building": 2, "ID": 15, "Coordinates": [{"x": 12, "y": -25, "z": 15}, {"x": 12, "y": -25, "z": 5}, {"x": 18, "y": -25, "z": 15}, {"x": 18, "y": -25, "z": 5}]}},
{"Timestamp": "2020-10-30 14:57:45", "File": "Energy%203D%20ENGT%20180%20Design%20PROJECT.ng3", "Camera": {"Position": {"x": 2.016, "y": -96.302, "z": 22.777}, "Direction": {"x": 0.015, "y": 0.993, "z": -0.12}, "Mode": "Rotate"}},
{"Timestamp": "2020-10-30 14:57:47", "File": "Energy%203D%20ENGT%20180%20Design%20PROJECT.ng3", "Edit Window": {"Type": "Window", "Building": 2, "ID": 16, "Coordinates": [{"x": 24, "y": -25, "z": 15}, {"x": 24, "y": -25, "z": 5}, {"x": 30, "y": -25, "z": 15}, {"x": 30, "y": -25, "z": 5}]}},
{"Timestamp": "2020-10-30 14:57:52", "File": "Energy%203D%20ENGT%20180%20Design%20PROJECT.ng3", "Camera": {"Position": {"x": 0.581, "y": 115.398, "z": 13.242}, "Direction": {"x": 0.028, "y": -0.999, "z": -0.03}, "Mode": "Rotate"}},
{"Timestamp": "2020-10-30 14:57:53", "File": "Energy%203D%20ENGT%20180%20Design%20PROJECT.ng3", "Camera": {"Position": {"x": 0.581, "y": 115.413, "z": 12.711}, "Direction": {"x": 0.028, "y": -0.999, "z": -0.025}, "Mode": "Rotate"}},
{"Timestamp": "2020-10-30 14:58:00", "File": "Energy%203D%20ENGT%20180%20Design%20PROJECT.ng3", "Camera": {"Position": {"x": 0.58, "y": 115.425, "z": 12.179}, "Direction": {"x": 0.028, "y": -0.999, "z": -0.02}, "Mode": "Rotate"}},
{"Timestamp": "2020-10-30 14:58:02", "File": "Energy%203D%20ENGT%20180%20Design%20PROJECT.ng3", "Edit Window": {"Type": "Window", "Building": 2, "ID": 19, "Coordinates": [{"x": 29, "y": 25, "z": 15}, {"x": 29, "y": 25, "z": 7}, {"x": 19, "y": 25, "z": 15}, {"x": 19, "y": 25, "z": 7}]}},
{"Timestamp": "2020-10-30 14:58:02", "File": "Energy%203D%20ENGT%20180%20Design%20PROJECT.ng3", "Camera": {"Position": {"x": -3.134, "y": 115.242, "z": 12.711}, "Direction": {"x": 0.063, "y": -0.998, "z": -0.025}, "Mode": "Rotate"}},
{"Timestamp": "2020-10-30 14:58:06", "File": "Energy%203D%20ENGT%20180%20Design%20PROJECT.ng3", "Camera": {"Position": {"x": -3.133, "y": 115.227, "z": 13.242}, "Direction": {"x": 0.063, "y": -0.998, "z": -0.03}, "Mode": "Rotate"}},
{"Timestamp": "2020-10-30 14:58:10", "File": "Energy%203D%20ENGT%20180%20Design%20PROJECT.ng3", "Edit Window": {"Type": "Window", "Building": 2, "ID": 19, "Coordinates": [{"x": 31, "y": 25, "z": 15}, {"x": 31, "y": 25, "z": 7}, {"x": 21, "y": 25, "z": 15}, {"x": 21, "y": 25, "z": 7}]}},
{"Timestamp": "2020-10-30 14:58:10", "File": "Energy%203D%20ENGT%20180%20Design%20PROJECT.ng3", "Camera": {"Position": {"x": 0.051, "y": 115.364, "z": 13.773}, "Direction": {"x": 0.033, "y": -0.999, "z": -0.035}, "Mode": "Rotate"}},
{"Timestamp": "2020-10-30 14:58:13", "File": "Energy%203D%20ENGT%20180%20Design%20PROJECT.ng3", "Edit Window": {"Type": "Window", "Building": 2, "ID": 19, "Coordinates": [{"x": 31, "y": 25, "z": 15}, {"x": 31, "y": 25, "z": 7}, {"x": 11, "y": 25, "z": 15}, {"x": 11, "y": 25, "z": 7}]}},
{"Timestamp": "2020-10-30 14:58:14", "File": "Energy%203D%20ENGT%20180%20Design%20PROJECT.ng3", "Camera": {"Position": {"x": 0.052, "y": 115.344, "z": 14.304}, "Direction": {"x": 0.033, "y": -0.999, "z": -0.04}, "Mode": "Rotate"}},
{"Timestamp": "2020-10-30 14:58:17", "File": "Energy%203D%20ENGT%20180%20Design%20PROJECT.ng3", "Edit Window": {"Type": "Window", "Building": 2, "ID": 20, "Coordinates": [{"x": -3, "y": 25, "z": 15}, {"x": -3, "y": 25, "z": 7}, {"x": -27, "y": 25, "z": 15}, {"x": -27, "y": 25, "z": 7}]}},
{"Timestamp": "2020-10-30 14:58:18", "File": "Energy%203D%20ENGT%20180%20Design%20PROJECT.ng3", "Camera": {"Position": {"x": -1.011, "y": 115.341, "z": 13.242}, "Direction": {"x": 0.043, "y": -0.999, "z": -0.03}, "Mode": "Rotate"}},
{"Timestamp": "2020-10-30 14:58:22", "File": "Energy%203D%20ENGT%20180%20Design%20PROJECT.ng3", "Camera": {"Position": {"x": 19.615, "y": 114.048, "z": 16.957}, "Direction": {"x": -0.151, "y": -0.986, "z": -0.065}, "Mode": "Rotate"}},
{"Timestamp": "2020-10-30 14:58:22", "File": "Energy%203D%20ENGT%20180%20Design%20PROJECT.ng3", "Camera": {"Position": {"x": 15.397, "y": 114.49, "z": 18.547}, "Direction": {"x": -0.111, "y": -0.991, "z": -0.08}, "Mode": "Rotate"}},
{"Timestamp": "2020-10-30 14:58:24", "File": "Energy%203D%20ENGT%20180%20Design%20PROJECT.ng3", "Edit Window": {"Type": "Window", "Building": 2, "ID": 19, "Coordinates": [{"x": 31, "y": 25, "z": 15}, {"x": 31, "y": 25, "z": 7}, {"x": 9, "y": 25, "z": 15}, {"x": 9, "y": 25, "z": 7}]}},
{"Timestamp": "2020-10-30 14:58:26", "File": "Energy%203D%20ENGT%20180%20Design%20PROJECT.ng3", "Camera": {"Position": {"x": 93.247, "y": -47.726, "z": 5.804}, "Direction": {"x": -0.843, "y": 0.536, "z": 0.04}, "Mode": "Rotate"}},
{"Timestamp": "2020-10-30 14:58:28", "File": "Energy%203D%20ENGT%20180%20Design%20PROJECT.ng3", "Camera": {"Position": {"x": 104.564, "y": -23.783, "z": 13.773}, "Direction": {"x": -0.95, "y": 0.31, "z": -0.035}, "Mode": "Rotate"}},
{"Timestamp": "2020-10-30 14:58:28", "File": "Energy%203D%20ENGT%20180%20Design%20PROJECT.ng3", "Camera": {"Position": {"x": 104.398, "y": -24.287, "z": 13.773}, "Direction": {"x": -0.948, "y": 0.315, "z": -0.035}, "Mode": "Rotate"}},
{"Timestamp": "2020-10-30 14:58:31", "File": "Energy%203D%20ENGT%20180%20Design%20PROJECT.ng3", "Edit Window": {"Type": "Window", "Building": 2, "ID": 17, "Coordinates": [{"x": 40, "y": -17, "z": 15}, {"x": 40, "y": -17, "z": 5}, {"x": 40, "y": -5, "z": 15}, {"x": 40, "y": -5, "z": 5}]}},
{"Timestamp": "2020-10-30 14:58:34", "File": "Energy%203D%20ENGT%20180%20Design%20PROJECT.ng3", "Edit Window": {"Type": "Window", "Building": 2, "ID": 18, "Coordinates": [{"x": 40, "y": 3, "z": 15}, {"x": 40, "y": 3, "z": 5}, {"x": 40, "y": 15, "z": 15}, {"x": 40, "y": 15, "z": 5}]}},
{"Timestamp": "2020-10-30 14:58:34", "File": "Energy%203D%20ENGT%20180%20Design%20PROJECT.ng3", "Camera": {"Position": {"x": 104.379, "y": -24.281, "z": 14.304}, "Direction": {"x": -0.948, "y": 0.315, "z": -0.04}, "Mode": "Rotate"}},
{"Timestamp": "2020-10-30 14:58:35", "File": "Energy%203D%20ENGT%20180%20Design%20PROJECT.ng3", "Camera": {"Position": {"x": 103.724, "y": -26.302, "z": 13.242}, "Direction": {"x": -0.942, "y": 0.334, "z": -0.03}, "Mode": "Rotate"}},
{"Timestamp": "2020-10-30 14:58:37", "File": "Energy%203D%20ENGT%20180%20Design%20PROJECT.ng3", "Camera": {"Position": {"x": 0.953, "y": -96.614, "z": 19.606}, "Direction": {"x": 0.025, "y": 0.996, "z": -0.09}, "Mode": "Rotate"}},
{"Timestamp": "2020-10-30 14:58:40", "File": "Energy%203D%20ENGT%20180%20Design%20PROJECT.ng3", "Camera": {"Position": {"x": 1.581, "y": -91.663, "z": 43.487}, "Direction": {"x": 0.019, "y": 0.949, "z": -0.315}, "Mode": "Rotate"}},
{"Timestamp": "2020-10-30 14:58:41", "File": "Energy%203D%20ENGT%20180%20Design%20PROJECT.ng3", "Camera": {"Position": {"x": 1.077, "y": -91.651, "z": 43.487}, "Direction": {"x": 0.024, "y": 0.949, "z": -0.315}, "Mode": "Rotate"}},
{"Timestamp": "2020-10-30 14:58:43", "File": "Energy%203D%20ENGT%20180%20Design%20PROJECT.ng3", "Edit Rack": {"Type": "Rack", "Building": 2, "ID": 29, "Coordinates": [{"x": -10.25, "y": -20.292, "z": 29.726}]}},
{"Timestamp": "2020-10-30 14:58:46", "File": "Energy%203D%20ENGT%20180%20Design%20PROJECT.ng3", "Edit Rack": {"Type": "Rack", "Building": 2, "ID": 29, "Coordinates": [{"x": -15.613, "y": -19.638, "z": 30.09}]}},
{"Timestamp": "2020-10-30 14:58:46", "File": "Energy%203D%20ENGT%20180%20Design%20PROJECT.ng3", "Camera": {"Position": {"x": 0.563, "y": -91.967, "z": 42.477}, "Direction": {"x": 0.029, "y": 0.952, "z": -0.305}, "Mode": "Rotate"}},
{"Timestamp": "2020-10-30 14:58:49", "File": "Energy%203D%20ENGT%20180%20Design%20PROJECT.ng3", "Camera": {"Position": {"x": 1.46, "y": -76.335, "z": 73.099}, "Direction": {"x": 0.02, "y": 0.805, "z": -0.593}, "Mode": "Rotate"}},
{"Timestamp": "2020-10-30 14:58:52", "File": "Energy%203D%20ENGT%20180%20Design%20PROJECT.ng3", "Edit Rack": {"Type": "Rack", "Building": 2, "ID": 31, "Coordinates": [{"x": 16.975, "y": -21.015, "z": 29.325}]}},
{"Timestamp": "2020-10-30 14:58:52", "File": "Energy%203D%20ENGT%20180%20Design%20PROJECT.ng3", "Camera": {"Position": {"x": 1.887, "y": -76.344, "z": 73.099}, "Direction": {"x": 0.016, "y": 0.805, "z": -0.593}, "Mode": "Rotate"}},
{"Timestamp": "2020-10-30 14:58:55", "File": "Energy%203D%20ENGT%20180%20Design%20PROJECT.ng3", "Edit Rack": {"Type": "Rack", "Building": 2, "ID": 31, "Coordinates": [{"x": 21.1, "y": -19.638, "z": 30.09}]}},
{"Timestamp": "2020-10-30 14:58:55", "File": "Energy%203D%20ENGT%20180%20Design%20PROJECT.ng3", "Camera": {"Position": {"x": 1.894, "y": -76.028, "z": 73.526}, "Direction": {"x": 0.016, "y": 0.802, "z": -0.597}, "Mode": "Rotate"}},
{"Timestamp": "2020-10-30 14:59:03", "File": "Energy%203D%20ENGT%20180%20Design%20PROJECT.ng3", "Edit Rack": {"Type": "Rack", "Building": 2, "ID": 31, "Coordinates": [{"x": 23.595, "y": -19.638, "z": 30.09}]}},
{"Timestamp": "2020-10-30 14:59:03", "File": "Energy%203D%20ENGT%20180%20Design%20PROJECT.ng3", "Camera": {"Position": {"x": 1.468, "y": -76.018, "z": 73.526}, "Direction": {"x": 0.02, "y": 0.802, "z": -0.597}, "Mode": "Rotate"}},
{"Timestamp": "2020-10-30 14:59:04", "File": "Energy%203D%20ENGT%20180%20Design%20PROJECT.ng3", "Camera": {"Position": {"x": 1.476, "y": -75.7, "z": 73.952}, "Direction": {"x": 0.02, "y": 0.799, "z": -0.601}, "Mode": "Rotate"}},
{"Timestamp": "2020-10-30 14:59:06", "File": "Energy%203D%20ENGT%20180%20Design%20PROJECT.ng3", "Edit Rack": {"Type": "Rack", "Building": 2, "ID": 29, "Coordinates": [{"x": -19.33, "y": -19.638, "z": 30.09}]}},
{"Timestamp": "2020-10-30 14:59:07", "File": "Energy%203D%20ENGT%20180%20Design%20PROJECT.ng3", "Camera": {"Position": {"x": -4.816, "y": -74.662, "z": 74.798}, "Direction": {"x": 0.079, "y": 0.789, "z": -0.609}, "Mode": "Rotate"}},
{"Timestamp": "2020-10-30 14:59:10", "File": "Energy%203D%20ENGT%20180%20Design%20PROJECT.ng3", "Edit Rack": {"Type": "Rack", "Building": 2, "ID": 29, "Coordinates": [{"x": -16.956, "y": -19.638, "z": 30.09}]}},
{"Timestamp": "2020-10-30 14:59:19", "File": "Energy%203D%20ENGT%20180%20Design%20PROJECT.ng3", "Camera": {"Position": {"x": -5.725, "y": -75.213, "z": 73.952}, "Direction": {"x": 0.088, "y": 0.794, "z": -0.601}, "Mode": "Rotate"}},
{"Timestamp": "2020-10-30 14:59:21", "File": "Energy%203D%20ENGT%20180%20Design%20PROJECT.ng3", "Camera": {"Position": {"x": 7.662, "y": -71.984, "z": 78.524}, "Direction": {"x": -0.038, "y": 0.764, "z": -0.644}, "Mode": "Rotate"}},
{"Timestamp": "2020-10-30 14:59:23", "File": "Energy%203D%20ENGT%20180%20Design%20PROJECT.ng3", "Edit Rack": {"Type": "Rack", "Building": 2, "ID": 29, "Coordinates": [{"x": -20.975, "y": -20.875, "z": 29.403}]}},
{"Timestamp": "2020-10-30 14:59:23", "File": "Energy%203D%20ENGT%20180%20Design%20PROJECT.ng3", "Camera": {"Position": {"x": 8.473, "y": -71.939, "z": 78.524}, "Direction": {"x": -0.046, "y": 0.763, "z": -0.644}, "Mode": "Rotate"}},
{"Timestamp": "2020-10-30 14:59:27", "File": "Energy%203D%20ENGT%20180%20Design%20PROJECT.ng3", "Add Rack": {"Type": "Rack", "Building": 2, "ID": 37, "Coordinates": [{"x": 0.887, "y": -20.05, "z": 29.861}]}},
{"Timestamp": "2020-10-30 14:59:28", "File": "Energy%203D%20ENGT%20180%20Design%20PROJECT.ng3", "Camera": {"Position": {"x": 8.879, "y": -71.914, "z": 78.524}, "Direction": {"x": -0.05, "y": 0.763, "z": -0.644}, "Mode": "Rotate"}},
{"Timestamp": "2020-10-30 14:59:31", "File": "Energy%203D%20ENGT%20180%20Design%20PROJECT.ng3", "Edit Rack": {"Type": "Rack", "Building": 2, "ID": 37, "Coordinates": [{"x": -2.186, "y": -20.05, "z": 29.861}]}},
{"Timestamp": "2020-10-30 14:59:33", "File": "Energy%203D%20ENGT%20180%20Design%20PROJECT.ng3", "Edit Rack": {"Type": "Rack", "Building": 2, "ID": 37, "Coordinates": [{"x": 3.362, "y": -19.638, "z": 30.09}]}},
{"Timestamp": "2020-10-30 14:59:33", "File": "Energy%203D%20ENGT%20180%20Design%20PROJECT.ng3", "Camera": {"Position": {"x": 8.857, "y": -71.571, "z": 78.929}, "Direction": {"x": -0.049, "y": 0.76, "z": -0.648}, "Mode": "Rotate"}},
{"Timestamp": "2020-10-30 14:59:37", "File": "Energy%203D%20ENGT%20180%20Design%20PROJECT.ng3", "Edit Rack": {"Type": "Rack", "Building": 2, "ID": 29, "Coordinates": [{"x": -16.438, "y": -19.225, "z": 30.319}]}},
{"Timestamp": "2020-10-30 14:59:38", "File": "Energy%203D%20ENGT%20180%20Design%20PROJECT.ng3", "Camera": {"Position": {"x": 9.26, "y": -71.544, "z": 78.929}, "Direction": {"x": -0.053, "y": 0.76, "z": -0.648}, "Mode": "Rotate"}},
{"Timestamp": "2020-10-30 14:59:39", "File": "Energy%203D%20ENGT%20180%20Design%20PROJECT.ng3", "Camera": {"Position": {"x": -11.433, "y": -73.402, "z": 75.218}, "Direction": {"x": 0.141, "y": 0.777, "z": -0.613}, "Mode": "Rotate"}},
{"Timestamp": "2020-10-30 14:59:39", "File": "Energy%203D%20ENGT%20180%20Design%20PROJECT.ng3", "Camera": {"Position": {"x": -11.492, "y": -73.722, "z": 74.798}, "Direction": {"x": 0.142, "y": 0.78, "z": -0.609}, "Mode": "Rotate"}},
{"Timestamp": "2020-10-30 14:59:42", "File": "Energy%203D%20ENGT%20180%20Design%20PROJECT.ng3", "Edit Rack": {"Type": "Rack", "Building": 2, "ID": 29, "Coordinates": [{"x": -17.675, "y": -19.638, "z": 30.09}]}},
{"Timestamp": "2020-10-30 14:59:42", "File": "Energy%203D%20ENGT%20180%20Design%20PROJECT.ng3", "Camera": {"Position": {"x": -10.607, "y": -73.548, "z": 75.218}, "Direction": {"x": 0.134, "y": 0.779, "z": -0.613}, "Mode": "Rotate"}},
{"Timestamp": "2020-10-30 14:59:46", "File": "Energy%203D%20ENGT%20180%20Design%20PROJECT.ng3", "Edit Rack": {"Type": "Rack", "Building": 2, "ID": 37, "Coordinates": [{"x": 2.537, "y": -19.638, "z": 30.09}]}},
{"Timestamp": "2020-10-30 14:59:46", "File": "Energy%203D%20ENGT%20180%20Design%20PROJECT.ng3", "Camera": {"Position": {"x": -10.551, "y": -73.226, "z": 75.637}, "Direction": {"x": 0.133, "y": 0.776, "z": -0.617}, "Mode": "Rotate"}},
{"Timestamp": "2020-10-30 14:59:48", "File": "Energy%203D%20ENGT%20180%20Design%20PROJECT.ng3", "Camera": {"Position": {"x": 6.917, "y": -73.705, "z": 76.47}, "Direction": {"x": -0.031, "y": 0.78, "z": -0.625}, "Mode": "Rotate"}},
{"Timestamp": "2020-10-30 14:59:51", "File": "Energy%203D%20ENGT%20180%20Design%20PROJECT.ng3", "Camera": {"Position": {"x": 11.406, "y": -72.732, "z": 77.297}, "Direction": {"x": -0.073, "y": 0.771, "z": -0.633}, "Mode": "Rotate"}},
{"Timestamp": "2020-10-30 14:59:54", "File": "Energy%203D%20ENGT%20180%20Design%20PROJECT.ng3", "Edit Rack": {"Type": "Rack", "Building": 2, "ID": 31, "Coordinates": [{"x": 22.75, "y": -19.638, "z": 30.09}]}},
{"Timestamp": "2020-10-30 14:59:55", "File": "Energy%203D%20ENGT%20180%20Design%20PROJECT.ng3", "Camera": {"Position": {"x": 10.996, "y": -72.77, "z": 77.297}, "Direction": {"x": -0.07, "y": 0.771, "z": -0.633}, "Mode": "Rotate"}},
{"Timestamp": "2020-10-30 14:59:56", "File": "Energy%203D%20ENGT%20180%20Design%20PROJECT.ng3", "Camera": {"Position": {"x": -5.829, "y": -76.156, "z": 72.67}, "Direction": {"x": 0.089, "y": 0.803, "z": -0.589}, "Mode": "Rotate"}},
{"Timestamp": "2020-10-30 14:59:59", "File": "Energy%203D%20ENGT%20180%20Design%20PROJECT.ng3", "Camera": {"Position": {"x": -5.626, "y": -78.329, "z": 69.627}, "Direction": {"x": 0.087, "y": 0.824, "z": -0.56}, "Mode": "Rotate"}},
{"Timestamp": "2020-10-30 15:00:00", "File": "Energy%203D%20ENGT%20180%20Design%20PROJECT.ng3", "Camera": {"Position": {"x": -5.189, "y": -78.374, "z": 69.627}, "Direction": {"x": 0.083, "y": 0.824, "z": -0.56}, "Mode": "Rotate"}},
{"Timestamp": "2020-10-30 15:00:00", "File": "Energy%203D%20ENGT%20180%20Design%20PROJECT.ng3", "Camera": {"Position": {"x": -5.159, "y": -78.077, "z": 70.066}, "Direction": {"x": 0.082, "y": 0.821, "z": -0.565}, "Mode": "Rotate"}},
{"Timestamp": "2020-10-30 15:00:14", "File": "Energy%203D%20ENGT%20180%20Design%20PROJECT.ng3", "BuildingCost": {"Foundation": 2, "Amount": 210530.09360535623}},
{"Timestamp": "2020-10-30 15:00:26", "File": "Energy%203D%20ENGT%20180%20Design%20PROJECT.ng3", "BuildingCost": {"Foundation": 2, "Amount": 210530.09360535623}},
{"Timestamp": "2020-10-30 15:00:33", "File": "Energy%203D%20ENGT%20180%20Design%20PROJECT.ng3", "Camera": {"Position": {"x": -93.861, "y": -28.685, "z": 29.082}, "Direction": {"x": 0.917, "y": 0.357, "z": -0.179}, "Mode": "Rotate"}},
{"Timestamp": "2020-10-30 15:00:34", "File": "Energy%203D%20ENGT%20180%20Design%20PROJECT.ng3", "Camera": {"Position": {"x": -95.886, "y": -23.299, "z": 28.559}, "Direction": {"x": 0.936, "y": 0.306, "z": -0.174}, "Mode": "Rotate"}},
{"Timestamp": "2020-10-30 15:00:37", "File": "Energy%203D%20ENGT%20180%20Design%20PROJECT.ng3", "Camera": {"Position": {"x": 32.877, "y": -92.612, "z": 18.547}, "Direction": {"x": -0.275, "y": 0.958, "z": -0.08}, "Mode": "Rotate"}},
{"Timestamp": "2020-10-30 15:00:39", "File": "Energy%203D%20ENGT%20180%20Design%20PROJECT.ng3", "Camera": {"Position": {"x": 27.235, "y": -94.067, "z": 18.547}, "Direction": {"x": -0.222, "y": 0.972, "z": -0.08}, "Mode": "Rotate"}},
{"Timestamp": "2020-10-30 15:00:43", "File": "Energy%203D%20ENGT%20180%20Design%20PROJECT.ng3", "Edit Wall": {"Type": "Wall", "Building": 2, "ID": 8, "Coordinates": [{"x": 40, "y": -25, "z": 1}, {"x": 40, "y": -25, "z": 23.5}, {"x": -35, "y": -25, "z": 1}, {"x": -35, "y": -25, "z": 23.5}]}},
{"Timestamp": "2020-10-30 15:00:43", "File": "Energy%203D%20ENGT%20180%20Design%20PROJECT.ng3", "Camera": {"Position": {"x": 26.709, "y": -94.142, "z": 19.077}, "Direction": {"x": -0.217, "y": 0.972, "z": -0.085}, "Mode": "Rotate"}},
{"Timestamp": "2020-10-30 15:00:45", "File": "Energy%203D%20ENGT%20180%20Design%20PROJECT.ng3", "Camera": {"Position": {"x": 97.172, "y": -37.248, "z": 29.604}, "Direction": {"x": -0.88, "y": 0.437, "z": -0.184}, "Mode": "Rotate"}},
{"Timestamp": "2020-10-30 15:00:45", "File": "Energy%203D%20ENGT%20180%20Design%20PROJECT.ng3", "Camera": {"Position": {"x": 97.259, "y": -37.291, "z": 29.082}, "Direction": {"x": -0.881, "y": 0.437, "z": -0.179}, "Mode": "Rotate"}},
{"Timestamp": "2020-10-30 15:00:47", "File": "Energy%203D%20ENGT%20180%20Design%20PROJECT.ng3", "Edit Wall": {"Type": "Wall", "Building": 2, "ID": 7, "Coordinates": [{"x": 40, "y": 25, "z": 1}, {"x": 40, "y": 25, "z": 23.5}, {"x": 40, "y": -25, "z": 1}, {"x": 40, "y": -25, "z": 23.5}]}},
{"Timestamp": "2020-10-30 15:00:49", "File": "Energy%203D%20ENGT%20180%20Design%20PROJECT.ng3", "Camera": {"Position": {"x": 47.909, "y": 100.564, "z": 41.463}, "Direction": {"x": -0.417, "y": -0.86, "z": -0.295}, "Mode": "Rotate"}},
{"Timestamp": "2020-10-30 15:00:49", "File": "Energy%203D%20ENGT%20180%20Design%20PROJECT.ng3", "Camera": {"Position": {"x": 47.384, "y": 100.641, "z": 41.97}, "Direction": {"x": -0.412, "y": -0.86, "z": -0.3}, "Mode": "Rotate"}},
{"Timestamp": "2020-10-30 15:00:51", "File": "Energy%203D%20ENGT%20180%20Design%20PROJECT.ng3", "Camera": {"Position": {"x": 46.228, "y": 98.227, "z": 49.477}, "Direction": {"x": -0.401, "y": -0.838, "z": -0.371}, "Mode": "Rotate"}},
{"Timestamp": "2020-10-30 15:00:51", "File": "Energy%203D%20ENGT%20180%20Design%20PROJECT.ng3", "Camera": {"Position": {"x": 46.758, "y": 98.189, "z": 48.983}, "Direction": {"x": -0.406, "y": -0.837, "z": -0.366}, "Mode": "Rotate"}},
{"Timestamp": "2020-10-30 15:00:54", "File": "Energy%203D%20ENGT%20180%20Design%20PROJECT.ng3", "Camera": {"Position": {"x": 44.932, "y": 95.523, "z": 56.284}, "Direction": {"x": -0.389, "y": -0.812, "z": -0.435}, "Mode": "Rotate"}},
{"Timestamp": "2020-10-30 15:00:54", "File": "Energy%203D%20ENGT%20180%20Design%20PROJECT.ng3", "Camera": {"Position": {"x": 45.032, "y": 95.73, "z": 55.804}, "Direction": {"x": -0.39, "y": -0.814, "z": -0.43}, "Mode": "Rotate"}},
{"Timestamp": "2020-10-30 15:00:57", "File": "Energy%203D%20ENGT%20180%20Design%20PROJECT.ng3", "Camera": {"Position": {"x": 43.018, "y": 92.593, "z": 62.864}, "Direction": {"x": -0.371, "y": -0.785, "z": -0.497}, "Mode": "Rotate"}},
{"Timestamp": "2020-10-30 15:00:58", "File": "Energy%203D%20ENGT%20180%20Design%20PROJECT.ng3", "Camera": {"Position": {"x": 6.258, "y": 109.191, "z": 45.999}, "Direction": {"x": -0.025, "y": -0.941, "z": -0.338}, "Mode": "Rotate"}},
{"Timestamp": "2020-10-30 15:01:00", "File": "Energy%203D%20ENGT%20180%20Design%20PROJECT.ng3", "Camera": {"Position": {"x": 4.236, "y": 105.812, "z": 54.36}, "Direction": {"x": -0.006, "y": -0.909, "z": -0.417}, "Mode": "Rotate"}},
{"Timestamp": "2020-10-30 15:01:01", "File": "Energy%203D%20ENGT%20180%20Design%20PROJECT.ng3", "Camera": {"Position": {"x": -44.325, "y": 103.922, "z": 15.366}, "Direction": {"x": 0.451, "y": -0.891, "z": -0.05}, "Mode": "Rotate"}},
{"Timestamp": "2020-10-30 15:01:03", "File": "Energy%203D%20ENGT%20180%20Design%20PROJECT.ng3", "Camera": {"Position": {"x": -43.428, "y": 102.151, "z": 31.169}, "Direction": {"x": 0.442, "y": -0.875, "z": -0.199}, "Mode": "Rotate"}},
{"Timestamp": "2020-10-30 15:01:04", "File": "Energy%203D%20ENGT%20180%20Design%20PROJECT.ng3", "Camera": {"Position": {"x": -40.619, "y": 103.52, "z": 31.169}, "Direction": {"x": 0.416, "y": -0.887, "z": -0.199}, "Mode": "Rotate"}},
{"Timestamp": "2020-10-30 15:01:06", "File": "Energy%203D%20ENGT%20180%20Design%20PROJECT.ng3", "Edit Wall": {"Type": "Wall", "Building": 2, "ID": 6, "Coordinates": [{"x": -35, "y": 25, "z": 1}, {"x": -35, "y": 25, "z": 23.5}, {"x": 40, "y": 25, "z": 1}, {"x": 40, "y": 25, "z": 23.5}]}},
{"Timestamp": "2020-10-30 15:01:08", "File": "Energy%203D%20ENGT%20180%20Design%20PROJECT.ng3", "Camera": {"Position": {"x": -101.917, "y": -3.262, "z": 12.711}, "Direction": {"x": 0.993, "y": 0.117, "z": -0.025}, "Mode": "Rotate"}},
{"Timestamp": "2020-10-30 15:01:11", "File": "Energy%203D%20ENGT%20180%20Design%20PROJECT.ng3", "Edit Wall": {"Type": "Wall", "Building": 2, "ID": 5, "Coordinates": [{"x": -35, "y": 25, "z": 1}, {"x": -35, "y": 25, "z": 23.5}, {"x": -35, "y": -25, "z": 1}, {"x": -35, "y": -25, "z": 23.5}]}},
{"Timestamp": "2020-10-30 15:01:13", "File": "Energy%203D%20ENGT%20180%20Design%20PROJECT.ng3", "Camera": {"Position": {"x": -77.532, "y": -55.416, "z": 33.248}, "Direction": {"x": 0.763, "y": 0.608, "z": -0.218}, "Mode": "Rotate"}},
{"Timestamp": "2020-10-30 15:01:14", "File": "Energy%203D%20ENGT%20180%20Design%20PROJECT.ng3", "Camera": {"Position": {"x": -77.208, "y": -55.821, "z": 33.248}, "Direction": {"x": 0.76, "y": 0.612, "z": -0.218}, "Mode": "Rotate"}},
{"Timestamp": "2020-10-30 15:01:15", "File": "Energy%203D%20ENGT%20180%20Design%20PROJECT.ng3", "Camera": {"Position": {"x": -67.527, "y": -69.764, "z": 8.991}, "Direction": {"x": 0.669, "y": 0.743, "z": 0.01}, "Mode": "Rotate"}},
{"Timestamp": "2020-10-30 15:01:16", "File": "Energy%203D%20ENGT%20180%20Design%20PROJECT.ng3", "Camera": {"Position": {"x": -33.134, "y": -90.438, "z": 14.304}, "Direction": {"x": 0.346, "y": 0.938, "z": -0.04}, "Mode": "Rotate"}},
{"Timestamp": "2020-10-30 15:01:17", "File": "Energy%203D%20ENGT%20180%20Design%20PROJECT.ng3", "Camera": {"Position": {"x": -32.8, "y": -90.531, "z": 15.002}, "Direction": {"x": 0.346, "y": 0.938, "z": -0.04}, "Mode": "Pan"}},
{"Timestamp": "2020-10-30 15:01:18", "File": "Energy%203D%20ENGT%20180%20Design%20PROJECT.ng3", "Camera": {"Position": {"x": -32.151, "y": -90.77, "z": 15.002}, "Direction": {"x": 0.346, "y": 0.938, "z": -0.04}, "Mode": "Pan"}},
{"Timestamp": "2020-10-30 15:01:21", "File": "Energy%203D%20ENGT%20180%20Design%20PROJECT.ng3", "Camera": {"Position": {"x": -32.151, "y": -90.744, "z": 15.701}, "Direction": {"x": 0.346, "y": 0.938, "z": -0.04}, "Mode": "Pan"}},
{"Timestamp": "2020-10-30 15:01:22", "File": "Energy%203D%20ENGT%20180%20Design%20PROJECT.ng3", "Camera": {"Position": {"x": -32.149, "y": -90.763, "z": 15.17}, "Direction": {"x": 0.346, "y": 0.938, "z": -0.035}, "Mode": "Rotate"}},
{"Timestamp": "2020-10-30 15:01:24", "File": "Energy%203D%20ENGT%20180%20Design%20PROJECT.ng3", "Camera": {"Position": {"x": -3.164, "y": -96.876, "z": 18.354}, "Direction": {"x": 0.073, "y": 0.995, "z": -0.065}, "Mode": "Rotate"}},
{"Timestamp": "2020-10-30 15:01:24", "File": "Energy%203D%20ENGT%20180%20Design%20PROJECT.ng3", "Camera": {"Position": {"x": -2.815, "y": -96.901, "z": 18.354}, "Direction": {"x": 0.073, "y": 0.995, "z": -0.065}, "Mode": "Pan"}},
{"Timestamp": "2020-10-30 15:01:27", "File": "Energy%203D%20ENGT%20180%20Design%20PROJECT.ng3", "Camera": {"Position": {"x": -3.344, "y": -96.861, "z": 18.354}, "Direction": {"x": 0.078, "y": 0.995, "z": -0.065}, "Mode": "Rotate"}},
{"Timestamp": "2020-10-30 15:01:32", "File": "Energy%203D%20ENGT%20180%20Design%20PROJECT.ng3", "Camera": {"Position": {"x": -2.29, "y": -96.806, "z": 20.474}, "Direction": {"x": 0.078, "y": 0.995, "z": -0.065}, "Mode": "Pan"}},
{"Timestamp": "2020-10-30 15:01:54", "File": "Energy%203D%20ENGT%20180%20Design%20PROJECT.ng3", "Camera": {"Position": {"x": -15.473, "y": 108.008, "z": 45.487}, "Direction": {"x": 0.202, "y": -0.932, "z": -0.3}, "Mode": "Rotate"}},
{"Timestamp": "2020-10-30 15:01:55", "File": "Energy%203D%20ENGT%20180%20Design%20PROJECT.ng3", "Camera": {"Position": {"x": 109.761, "y": 25.058, "z": 29.979}, "Direction": {"x": -0.976, "y": -0.152, "z": -0.154}, "Mode": "Rotate"}},
{"Timestamp": "2020-10-30 15:01:56", "File": "Energy%203D%20ENGT%20180%20Design%20PROJECT.ng3", "Camera": {"Position": {"x": 109.679, "y": 25.577, "z": 29.979}, "Direction": {"x": -0.976, "y": -0.157, "z": -0.154}, "Mode": "Rotate"}},
{"Timestamp": "2020-10-30 15:01:57", "File": "Energy%203D%20ENGT%20180%20Design%20PROJECT.ng3", "Camera": {"Position": {"x": 53.756, "y": -85.09, "z": 26.822}, "Direction": {"x": -0.449, "y": 0.885, "z": -0.125}, "Mode": "Rotate"}},
{"Timestamp": "2020-10-30 15:02:01", "File": "Energy%203D%20ENGT%20180%20Design%20PROJECT.ng3", "Camera": {"Position": {"x": -34.228, "y": -88.93, "z": 23.653}, "Direction": {"x": 0.378, "y": 0.921, "z": -0.095}, "Mode": "Rotate"}},
{"Timestamp": "2020-10-30 15:02:04", "File": "Energy%203D%20ENGT%20180%20Design%20PROJECT.ng3", "Camera": {"Position": {"x": -60.562, "y": -73.379, "z": 23.123}, "Direction": {"x": 0.626, "y": 0.774, "z": -0.09}, "Mode": "Rotate"}},
{"Timestamp": "2020-10-30 15:02:05", "File": "Energy%203D%20ENGT%20180%20Design%20PROJECT.ng3", "Camera": {"Position": {"x": -60.531, "y": -73.341, "z": 23.653}, "Direction": {"x": 0.626, "y": 0.774, "z": -0.095}, "Mode": "Rotate"}},
{"Timestamp": "2020-10-30 15:02:06", "File": "Energy%203D%20ENGT%20180%20Design%20PROJECT.ng3", "Camera": {"Position": {"x": -86.766, "y": 58.313, "z": 29.454}, "Direction": {"x": 0.873, "y": -0.465, "z": -0.149}, "Mode": "Rotate"}},
{"Timestamp": "2020-10-30 15:02:10", "File": "Energy%203D%20ENGT%20180%20Design%20PROJECT.ng3", "Camera": {"Position": {"x": 30.323, "y": -92.669, "z": 33.121}, "Direction": {"x": -0.229, "y": 0.956, "z": -0.184}, "Mode": "Rotate"}},
{"Timestamp": "2020-10-30 15:02:19", "File": "Energy%203D%20ENGT%20180%20Design%20PROJECT.ng3", "BuildingCost": {"Foundation": 2, "Amount": 199999.51941097947}},
{"Timestamp": "2020-10-30 15:02:23", "File": "Energy%203D%20ENGT%20180%20Design%20PROJECT.ng3", "Camera": {"Position": {"x": 29.814, "y": -92.79, "z": 33.121}, "Direction": {"x": -0.224, "y": 0.957, "z": -0.184}, "Mode": "Rotate"}},
{"Timestamp": "2020-10-30 15:02:29", "File": "Energy%203D%20ENGT%20180%20Design%20PROJECT.ng3", "Camera": {"Position": {"x": 29.306, "y": -92.907, "z": 33.121}, "Direction": {"x": -0.219, "y": 0.958, "z": -0.184}, "Mode": "Rotate"}},
{"Timestamp": "2020-10-30 15:02:30", "File": "Energy%203D%20ENGT%20180%20Design%20PROJECT.ng3", "Camera": {"Position": {"x": 29.814, "y": -92.79, "z": 33.121}, "Direction": {"x": -0.224, "y": 0.957, "z": -0.184}, "Mode": "Rotate"}},
{"Timestamp": "2020-10-30 15:02:32", "File": "Energy%203D%20ENGT%20180%20Design%20PROJECT.ng3", "Camera": {"Position": {"x": 29.306, "y": -92.907, "z": 33.121}, "Direction": {"x": -0.219, "y": 0.958, "z": -0.184}, "Mode": "Rotate"}},
{"Timestamp": "2020-10-30 15:02:37", "File": "Energy%203D%20ENGT%20180%20Design%20PROJECT.ng3", "Camera": {"Position": {"x": 29.836, "y": -92.884, "z": 32.599}, "Direction": {"x": -0.224, "y": 0.958, "z": -0.179}, "Mode": "Rotate"}},
{"Timestamp": "2020-10-30 15:02:45", "File": "Energy%203D%20ENGT%20180%20Design%20PROJECT.ng3", "Edit HipRoof": {"Type": "HipRoof", "Building": 2, "ID": 9, "Coordinates": [{"x": 2.5, "y": 0, "z": 33.5}, {"x": -17.25, "y": 0, "z": 33.5}, {"x": 22.25, "y": 0, "z": 33.5}]}},
{"Timestamp": "2020-10-30 15:02:49", "File": "Energy%203D%20ENGT%20180%20Design%20PROJECT.ng3", "Edit HipRoof": {"Type": "HipRoof", "Building": 2, "ID": 9, "Coordinates": [{"x": 2.5, "y": 0, "z": 36}, {"x": -17.25, "y": 0, "z": 36}, {"x": 22.25, "y": 0, "z": 36}]}},
{"Timestamp": "2020-10-30 15:02:50", "File": "Energy%203D%20ENGT%20180%20Design%20PROJECT.ng3", "Camera": {"Position": {"x": 29.327, "y": -93.001, "z": 32.599}, "Direction": {"x": -0.22, "y": 0.959, "z": -0.179}, "Mode": "Rotate"}},
{"Timestamp": "2020-10-30 15:02:52", "File": "Energy%203D%20ENGT%20180%20Design%20PROJECT.ng3", "Camera": {"Position": {"x": -35.469, "y": -83.925, "z": 44.472}, "Direction": {"x": 0.39, "y": 0.874, "z": -0.291}, "Mode": "Rotate"}},
{"Timestamp": "2020-10-30 15:03:01", "File": "Energy%203D%20ENGT%20180%20Design%20PROJECT.ng3", "BuildingCost": [{"Foundation": 2, "Amount": 197878.76641669933}]},
{"Timestamp": "2020-10-30 15:03:04", "File": "Energy%203D%20ENGT%20180%20Design%20PROJECT.ng3", "Camera": {"Position": {"x": 11.3, "y": -97.03, "z": 19.944}, "Direction": {"x": -0.05, "y": 0.997, "z": -0.06}, "Mode": "Rotate"}},
{"Timestamp": "2020-10-30 15:03:10", "File": "Energy%203D%20ENGT%20180%20Design%20PROJECT.ng3", "BuildingCost": {"Foundation": 2, "Amount": 197878.76641669933}},
{"Timestamp": "2020-10-30 15:03:14", "File": "Energy%203D%20ENGT%20180%20Design%20PROJECT.ng3", "Edit Window": {"Type": "Window", "Building": 2, "ID": 14, "Coordinates": [{"x": -16, "y": -25, "z": 13}, {"x": -16, "y": -25, "z": 4.6}, {"x": -6, "y": -25, "z": 13}, {"x": -6, "y": -25, "z": 4.6}]}},
{"Timestamp": "2020-10-30 15:03:14", "File": "Energy%203D%20ENGT%20180%20Design%20PROJECT.ng3", "Camera": {"Position": {"x": 9.18, "y": -97.115, "z": 19.944}, "Direction": {"x": -0.03, "y": 0.998, "z": -0.06}, "Mode": "Rotate"}},
{"Timestamp": "2020-10-30 15:03:15", "File": "Energy%203D%20ENGT%20180%20Design%20PROJECT.ng3", "Edit Window": {"Type": "Window", "Building": 2, "ID": 15, "Coordinates": [{"x": 12, "y": -25, "z": 13.6}, {"x": 12, "y": -25, "z": 4.6}, {"x": 18, "y": -25, "z": 13.6}, {"x": 18, "y": -25, "z": 4.6}]}},
{"Timestamp": "2020-10-30 15:03:15", "File": "Energy%203D%20ENGT%20180%20Design%20PROJECT.ng3", "Camera": {"Position": {"x": 9.71, "y": -97.098, "z": 19.944}, "Direction": {"x": -0.035, "y": 0.998, "z": -0.06}, "Mode": "Rotate"}},
{"Timestamp": "2020-10-30 15:03:18", "File": "Energy%203D%20ENGT%20180%20Design%20PROJECT.ng3", "Edit Window": {"Type": "Window", "Building": 2, "ID": 15, "Coordinates": [{"x": 8, "y": -25, "z": 13}, {"x": 8, "y": -25, "z": 4.6}, {"x": 18, "y": -25, "z": 13}, {"x": 18, "y": -25, "z": 4.6}]}},
{"Timestamp": "2020-10-30 15:03:22", "File": "Energy%203D%20ENGT%20180%20Design%20PROJECT.ng3", "Edit Window": {"Type": "Window", "Building": 2, "ID": 16, "Coordinates": [{"x": 24, "y": -25, "z": 13}, {"x": 24, "y": -25, "z": 4.6}, {"x": 34, "y": -25, "z": 13}, {"x": 34, "y": -25, "z": 4.6}]}},
{"Timestamp": "2020-10-30 15:03:22", "File": "Energy%203D%20ENGT%20180%20Design%20PROJECT.ng3", "Camera": {"Position": {"x": 9.18, "y": -97.115, "z": 19.944}, "Direction": {"x": -0.03, "y": 0.998, "z": -0.06}, "Mode": "Rotate"}},
{"Timestamp": "2020-10-30 15:03:26", "File": "Energy%203D%20ENGT%20180%20Design%20PROJECT.ng3", "Edit Window": {"Type": "Window", "Building": 2, "ID": 13, "Coordinates": [{"x": -28, "y": -25, "z": 13}, {"x": -28, "y": -25, "z": 4.6}, {"x": -22, "y": -25, "z": 13}, {"x": -22, "y": -25, "z": 4.6}]}},
{"Timestamp": "2020-10-30 15:03:29", "File": "Energy%203D%20ENGT%20180%20Design%20PROJECT.ng3", "Edit Window": {"Type": "Window", "Building": 2, "ID": 13, "Coordinates": [{"x": -32, "y": -25, "z": 13}, {"x": -32, "y": -25, "z": 4.6}, {"x": -22, "y": -25, "z": 13}, {"x": -22, "y": -25, "z": 4.6}]}},
{"Timestamp": "2020-10-30 15:03:30", "File": "Energy%203D%20ENGT%20180%20Design%20PROJECT.ng3", "Camera": {"Position": {"x": 9.71, "y": -97.098, "z": 19.944}, "Direction": {"x": -0.035, "y": 0.998, "z": -0.06}, "Mode": "Rotate"}},
{"Timestamp": "2020-10-30 15:03:36", "File": "Energy%203D%20ENGT%20180%20Design%20PROJECT.ng3", "BuildingCost": {"Foundation": 2, "Amount": 200621.6236598285}},
{"Timestamp": "2020-10-30 15:03:36", "File": "Energy%203D%20ENGT%20180%20Design%20PROJECT.ng3", "Camera": {"Position": {"x": 9.709, "y": -97.065, "z": 20.474}, "Direction": {"x": -0.035, "y": 0.997, "z": -0.065}, "Mode": "Rotate"}},
{"Timestamp": "2020-10-30 15:03:39", "File": "Energy%203D%20ENGT%20180%20Design%20PROJECT.ng3", "Edit Window": {"Type": "Window", "Building": 2, "ID": 13, "Coordinates": [{"x": -32, "y": -25, "z": 21}, {"x": -32, "y": -25, "z": 4.6}, {"x": -22, "y": -25, "z": 21}, {"x": -22, "y": -25, "z": 4.6}]}},
{"Timestamp": "2020-10-30 15:03:39", "File": "Energy%203D%20ENGT%20180%20Design%20PROJECT.ng3", "Camera": {"Position": {"x": 8.65, "y": -97.16, "z": 19.413}, "Direction": {"x": -0.025, "y": 0.998, "z": -0.055}, "Mode": "Rotate"}},
{"Timestamp": "2020-10-30 15:03:43", "File": "Energy%203D%20ENGT%20180%20Design%20PROJECT.ng3", "Edit Window": {"Type": "Window", "Building": 2, "ID": 14, "Coordinates": [{"x": -18, "y": -25, "z": 21}, {"x": -18, "y": -25, "z": 4.6}, {"x": -6, "y": -25, "z": 21}, {"x": -6, "y": -25, "z": 4.6}]}},
{"Timestamp": "2020-10-30 15:03:45", "File": "Energy%203D%20ENGT%20180%20Design%20PROJECT.ng3", "Edit Window": {"Type": "Window", "Building": 2, "ID": 15, "Coordinates": [{"x": 8, "y": -25, "z": 21}, {"x": 8, "y": -25, "z": 4.6}, {"x": 18, "y": -25, "z": 21}, {"x": 18, "y": -25, "z": 4.6}]}},
{"Timestamp": "2020-10-30 15:03:45", "File": "Energy%203D%20ENGT%20180%20Design%20PROJECT.ng3", "Camera": {"Position": {"x": 8.65, "y": -97.13, "z": 19.944}, "Direction": {"x": -0.025, "y": 0.998, "z": -0.06}, "Mode": "Rotate"}},
{"Timestamp": "2020-10-30 15:03:46", "File": "Energy%203D%20ENGT%20180%20Design%20PROJECT.ng3", "Camera": {"Position": {"x": 9.18, "y": -97.115, "z": 19.944}, "Direction": {"x": -0.03, "y": 0.998, "z": -0.06}, "Mode": "Rotate"}},
{"Timestamp": "2020-10-30 15:03:48", "File": "Energy%203D%20ENGT%20180%20Design%20PROJECT.ng3", "Edit Window": {"Type": "Window", "Building": 2, "ID": 16, "Coordinates": [{"x": 24, "y": -25, "z": 21}, {"x": 24, "y": -25, "z": 4.6}, {"x": 34, "y": -25, "z": 21}, {"x": 34, "y": -25, "z": 4.6}]}},
{"Timestamp": "2020-10-30 15:03:48", "File": "Energy%203D%20ENGT%20180%20Design%20PROJECT.ng3", "Camera": {"Position": {"x": 9.182, "y": -97.173, "z": 18.883}, "Direction": {"x": -0.03, "y": 0.998, "z": -0.05}, "Mode": "Rotate"}},
{"Timestamp": "2020-10-30 15:03:49", "File": "Energy%203D%20ENGT%20180%20Design%20PROJECT.ng3", "Camera": {"Position": {"x": 9.711, "y": -97.128, "z": 19.413}, "Direction": {"x": -0.035, "y": 0.998, "z": -0.055}, "Mode": "Rotate"}},
{"Timestamp": "2020-10-30 15:03:56", "File": "Energy%203D%20ENGT%20180%20Design%20PROJECT.ng3", "BuildingCost": {"Foundation": 2, "Amount": 208683.82365732171}},
{"Timestamp": "2020-10-30 15:03:59", "File": "Energy%203D%20ENGT%20180%20Design%20PROJECT.ng3", "Edit Window": {"Type": "Window", "Building": 2, "ID": 16, "Coordinates": [{"x": 24, "y": -25, "z": 13}, {"x": 24, "y": -25, "z": 4.6}, {"x": 34, "y": -25, "z": 13}, {"x": 34, "y": -25, "z": 4.6}]}},
{"Timestamp": "2020-10-30 15:04:00", "File": "Energy%203D%20ENGT%20180%20Design%20PROJECT.ng3", "Camera": {"Position": {"x": 10.241, "y": -97.108, "z": 19.413}, "Direction": {"x": -0.04, "y": 0.998, "z": -0.055}, "Mode": "Rotate"}},
{"Timestamp": "2020-10-30 15:04:05", "File": "Energy%203D%20ENGT%20180%20Design%20PROJECT.ng3", "Edit Window": {"Type": "Window", "Building": 2, "ID": 15, "Coordinates": [{"x": 8, "y": -25, "z": 11}, {"x": 8, "y": -25, "z": 4.6}, {"x": 14, "y": -25, "z": 11}, {"x": 14, "y": -25, "z": 4.6}]}},
{"Timestamp": "2020-10-30 15:04:05", "File": "Energy%203D%20ENGT%20180%20Design%20PROJECT.ng3", "Camera": {"Position": {"x": 10.24, "y": -97.078, "z": 19.944}, "Direction": {"x": -0.04, "y": 0.997, "z": -0.06}, "Mode": "Rotate"}},
{"Timestamp": "2020-10-30 15:04:05", "File": "Energy%203D%20ENGT%20180%20Design%20PROJECT.ng3", "Camera": {"Position": {"x": 10.241, "y": -97.108, "z": 19.413}, "Direction": {"x": -0.04, "y": 0.998, "z": -0.055}, "Mode": "Rotate"}},
{"Timestamp": "2020-10-30 15:04:08", "File": "Energy%203D%20ENGT%20180%20Design%20PROJECT.ng3", "Edit Window": {"Type": "Window", "Building": 2, "ID": 16, "Coordinates": [{"x": 28, "y": -25, "z": 11}, {"x": 28, "y": -25, "z": 4.6}, {"x": 34, "y": -25, "z": 11}, {"x": 34, "y": -25, "z": 4.6}]}},
{"Timestamp": "2020-10-30 15:04:08", "File": "Energy%203D%20ENGT%20180%20Design%20PROJECT.ng3", "Camera": {"Position": {"x": 10.24, "y": -97.078, "z": 19.944}, "Direction": {"x": -0.04, "y": 0.997, "z": -0.06}, "Mode": "Rotate"}},
{"Timestamp": "2020-10-30 15:04:13", "File": "Energy%203D%20ENGT%20180%20Design%20PROJECT.ng3", "Edit Window": {"Type": "Window", "Building": 2, "ID": 14, "Coordinates": [{"x": -18, "y": -25, "z": 11}, {"x": -18, "y": -25, "z": 4.6}, {"x": -12, "y": -25, "z": 11}, {"x": -12, "y": -25, "z": 4.6}]}},
{"Timestamp": "2020-10-30 15:04:13", "File": "Energy%203D%20ENGT%20180%20Design%20PROJECT.ng3", "Camera": {"Position": {"x": 10.239, "y": -97.045, "z": 20.474}, "Direction": {"x": -0.04, "y": 0.997, "z": -0.065}, "Mode": "Rotate"}},
{"Timestamp": "2020-10-30 15:04:16", "File": "Energy%203D%20ENGT%20180%20Design%20PROJECT.ng3", "Edit Window": {"Type": "Window", "Building": 2, "ID": 13, "Coordinates": [{"x": -32, "y": -25, "z": 11}, {"x": -32, "y": -25, "z": 4.6}, {"x": -26, "y": -25, "z": 11}, {"x": -26, "y": -25, "z": 4.6}]}},
{"Timestamp": "2020-10-30 15:04:16", "File": "Energy%203D%20ENGT%20180%20Design%20PROJECT.ng3", "Camera": {"Position": {"x": 10.769, "y": -97.022, "z": 20.474}, "Direction": {"x": -0.045, "y": 0.997, "z": -0.065}, "Mode": "Rotate"}},
{"Timestamp": "2020-10-30 15:04:19", "File": "Energy%203D%20ENGT%20180%20Design%20PROJECT.ng3", "Edit Window": {"Type": "Window", "Building": 2, "ID": 13, "Coordinates": [{"x": -30, "y": -25, "z": 11}, {"x": -30, "y": -25, "z": 4.6}, {"x": -24, "y": -25, "z": 11}, {"x": -24, "y": -25, "z": 4.6}]}},
{"Timestamp": "2020-10-30 15:04:19", "File": "Energy%203D%20ENGT%20180%20Design%20PROJECT.ng3", "Camera": {"Position": {"x": 4.407, "y": -97.118, "z": 20.474}, "Direction": {"x": 0.015, "y": 0.998, "z": -0.065}, "Mode": "Rotate"}},
{"Timestamp": "2020-10-30 15:04:21", "File": "Energy%203D%20ENGT%20180%20Design%20PROJECT.ng3", "Edit Window": {"Type": "Window", "Building": 2, "ID": 16, "Coordinates": [{"x": 24, "y": -25, "z": 9}, {"x": 24, "y": -25, "z": 2.6}, {"x": 30, "y": -25, "z": 9}, {"x": 30, "y": -25, "z": 2.6}]}},
{"Timestamp": "2020-10-30 15:04:21", "File": "Energy%203D%20ENGT%20180%20Design%20PROJECT.ng3", "Camera": {"Position": {"x": 16.538, "y": -96.125, "z": 25.766}, "Direction": {"x": -0.099, "y": 0.988, "z": -0.115}, "Mode": "Rotate"}},
{"Timestamp": "2020-10-30 15:04:23", "File": "Energy%203D%20ENGT%20180%20Design%20PROJECT.ng3", "Edit Window": {"Type": "Window", "Building": 2, "ID": 16, "Coordinates": [{"x": 24, "y": -25, "z": 11}, {"x": 24, "y": -25, "z": 4.6}, {"x": 30, "y": -25, "z": 11}, {"x": 30, "y": -25, "z": 4.6}]}},
{"Timestamp": "2020-10-30 15:04:23", "File": "Energy%203D%20ENGT%20180%20Design%20PROJECT.ng3", "Camera": {"Position": {"x": 17.113, "y": -96.545, "z": 20.474}, "Direction": {"x": -0.105, "y": 0.992, "z": -0.065}, "Mode": "Rotate"}},
{"Timestamp": "2020-10-30 15:04:25", "File": "Energy%203D%20ENGT%20180%20Design%20PROJECT.ng3", "Edit Window": {"Type": "Window", "Building": 2, "ID": 15, "Coordinates": [{"x": 12, "y": -25, "z": 11}, {"x": 12, "y": -25, "z": 4.6}, {"x": 18, "y": -25, "z": 11}, {"x": 18, "y": -25, "z": 4.6}]}},
{"Timestamp": "2020-10-30 15:04:25", "File": "Energy%203D%20ENGT%20180%20Design%20PROJECT.ng3", "Camera": {"Position": {"x": 17.641, "y": -96.489, "z": 20.474}, "Direction": {"x": -0.11, "y": 0.992, "z": -0.065}, "Mode": "Rotate"}},
{"Timestamp": "2020-10-30 15:04:26", "File": "Energy%203D%20ENGT%20180%20Design%20PROJECT.ng3", "Camera": {"Position": {"x": 17.644, "y": -96.522, "z": 19.944}, "Direction": {"x": -0.11, "y": 0.992, "z": -0.06}, "Mode": "Rotate"}},
{"Timestamp": "2020-10-30 15:04:44", "File": "Energy%203D%20ENGT%20180%20Design%20PROJECT.ng3", "BuildingCost": {"Foundation": 2, "Amount": 196466.88082274006}},
{"Timestamp": "2020-10-30 15:04:47", "File": "Energy%203D%20ENGT%20180%20Design%20PROJECT.ng3", "Camera": {"Position": {"x": 88.332, "y": 75.836, "z": 19.944}, "Direction": {"x": -0.775, "y": -0.63, "z": -0.06}, "Mode": "Rotate"}},
{"Timestamp": "2020-10-30 15:04:48", "File": "Energy%203D%20ENGT%20180%20Design%20PROJECT.ng3", "Camera": {"Position": {"x": 111.712, "y": 19.257, "z": 17.29}, "Direction": {"x": -0.995, "y": -0.097, "z": -0.035}, "Mode": "Rotate"}},
{"Timestamp": "2020-10-30 15:04:52", "File": "Energy%203D%20ENGT%20180%20Design%20PROJECT.ng3", "Edit Window": {"Type": "Window", "Building": 2, "ID": 18, "Coordinates": [{"x": 40, "y": 3, "z": 11}, {"x": 40, "y": 3, "z": 4.6}, {"x": 40, "y": 11, "z": 11}, {"x": 40, "y": 11, "z": 4.6}]}},
{"Timestamp": "2020-10-30 15:04:52", "File": "Energy%203D%20ENGT%20180%20Design%20PROJECT.ng3", "Camera": {"Position": {"x": 111.693, "y": 19.255, "z": 17.821}, "Direction": {"x": -0.994, "y": -0.097, "z": -0.04}, "Mode": "Rotate"}},
{"Timestamp": "2020-10-30 15:04:53", "File": "Energy%203D%20ENGT%20180%20Design%20PROJECT.ng3", "Edit Window": {"Type": "Window", "Building": 2, "ID": 17, "Coordinates": [{"x": 40, "y": -17, "z": 13.6}, {"x": 40, "y": -17, "z": 4.6}, {"x": 40, "y": -5, "z": 13.6}, {"x": 40, "y": -5, "z": 4.6}]}},
{"Timestamp": "2020-10-30 15:04:54", "File": "Energy%203D%20ENGT%20180%20Design%20PROJECT.ng3", "Edit Window": {"Type": "Window", "Building": 2, "ID": 17, "Coordinates": [{"x": 40, "y": -17, "z": 11}, {"x": 40, "y": -17, "z": 4.6}, {"x": 40, "y": -11, "z": 11}, {"x": 40, "y": -11, "z": 4.6}]}},
{"Timestamp": "2020-10-30 15:04:59", "File": "Energy%203D%20ENGT%20180%20Design%20PROJECT.ng3", "BuildingCost": {"Foundation": 2, "Amount": 193583.13809845765}},
{"Timestamp": "2020-10-30 15:05:01", "File": "Energy%203D%20ENGT%20180%20Design%20PROJECT.ng3", "Camera": {"Position": {"x": 111.67, "y": 19.253, "z": 18.352}, "Direction": {"x": -0.994, "y": -0.097, "z": -0.045}, "Mode": "Rotate"}},
{"Timestamp": "2020-10-30 15:05:02", "File": "Energy%203D%20ENGT%20180%20Design%20PROJECT.ng3", "Edit Window": {"Type": "Window", "Building": 2, "ID": 18, "Coordinates": [{"x": 40, "y": 3, "z": 11}, {"x": 40, "y": 3, "z": 5}, {"x": 40, "y": 11, "z": 11}, {"x": 40, "y": 11, "z": 5}]}},
{"Timestamp": "2020-10-30 15:05:02", "File": "Energy%203D%20ENGT%20180%20Design%20PROJECT.ng3", "Camera": {"Position": {"x": 111.72, "y": 18.725, "z": 18.352}, "Direction": {"x": -0.995, "y": -0.092, "z": -0.045}, "Mode": "Rotate"}},
{"Timestamp": "2020-10-30 15:05:02", "File": "Energy%203D%20ENGT%20180%20Design%20PROJECT.ng3", "Camera": {"Position": {"x": 112.122, "y": 12.899, "z": 17.821}, "Direction": {"x": -0.999, "y": -0.037, "z": -0.04}, "Mode": "Rotate"}},
{"Timestamp": "2020-10-30 15:05:03", "File": "Energy%203D%20ENGT%20180%20Design%20PROJECT.ng3", "Camera": {"Position": {"x": 112.14, "y": 12.368, "z": 17.821}, "Direction": {"x": -0.999, "y": -0.032, "z": -0.04}, "Mode": "Rotate"}},
{"Timestamp": "2020-10-30 15:05:04", "File": "Energy%203D%20ENGT%20180%20Design%20PROJECT.ng3", "Edit Window": {"Type": "Window", "Building": 2, "ID": 18, "Coordinates": [{"x": 40, "y": 5, "z": 11}, {"x": 40, "y": 5, "z": 5}, {"x": 40, "y": 11, "z": 11}, {"x": 40, "y": 11, "z": 5}]}},
{"Timestamp": "2020-10-30 15:05:06", "File": "Energy%203D%20ENGT%20180%20Design%20PROJECT.ng3", "Camera": {"Position": {"x": 3.195, "y": 114.279, "z": 27.349}, "Direction": {"x": 0.026, "y": -0.991, "z": -0.13}, "Mode": "Rotate"}},
{"Timestamp": "2020-10-30 15:05:10", "File": "Energy%203D%20ENGT%20180%20Design%20PROJECT.ng3", "Edit Window": {"Type": "Window", "Building": 2, "ID": 19, "Coordinates": [{"x": 23, "y": 25, "z": 13.6}, {"x": 23, "y": 25, "z": 7}, {"x": 9, "y": 25, "z": 13.6}, {"x": 9, "y": 25, "z": 7}]}},
{"Timestamp": "2020-10-30 15:05:10", "File": "Energy%203D%20ENGT%20180%20Design%20PROJECT.ng3", "Camera": {"Position": {"x": 3.724, "y": 114.221, "z": 27.876}, "Direction": {"x": 0.021, "y": -0.991, "z": -0.135}, "Mode": "Rotate"}},
{"Timestamp": "2020-10-30 15:05:14", "File": "Energy%203D%20ENGT%20180%20Design%20PROJECT.ng3", "Edit Window": {"Type": "Window", "Building": 2, "ID": 20, "Coordinates": [{"x": -3, "y": 25, "z": 13.6}, {"x": -3, "y": 25, "z": 7}, {"x": -15, "y": 25, "z": 13.6}, {"x": -15, "y": 25, "z": 7}]}},
{"Timestamp": "2020-10-30 15:05:16", "File": "Energy%203D%20ENGT%20180%20Design%20PROJECT.ng3", "Edit Window": {"Type": "Window", "Building": 2, "ID": 20, "Coordinates": [{"x": -3, "y": 25, "z": 13.6}, {"x": -3, "y": 25, "z": 7}, {"x": -17, "y": 25, "z": 13.6}, {"x": -17, "y": 25, "z": 7}]}},
{"Timestamp": "2020-10-30 15:05:21", "File": "Energy%203D%20ENGT%20180%20Design%20PROJECT.ng3", "BuildingCost": {"Foundation": 2, "Amount": 189893.023855359}},
{"Timestamp": "2020-10-30 15:05:22", "File": "Energy%203D%20ENGT%20180%20Design%20PROJECT.ng3", "Camera": {"Position": {"x": 73.868, "y": -71.947, "z": 25.766}, "Direction": {"x": -0.639, "y": 0.761, "z": -0.115}, "Mode": "Rotate"}},
{"Timestamp": "2020-10-30 15:05:24", "File": "Energy%203D%20ENGT%20180%20Design%20PROJECT.ng3", "Camera": {"Position": {"x": -8.993, "y": -96.065, "z": 20.474}, "Direction": {"x": 0.141, "y": 0.988, "z": -0.065}, "Mode": "Rotate"}},
{"Timestamp": "2020-10-30 15:05:38", "File": "Energy%203D%20ENGT%20180%20Design%20PROJECT.ng3", "Camera": {"Position": {"x": -62.044, "y": -69.942, "z": 34.686}, "Direction": {"x": 0.64, "y": 0.742, "z": -0.199}, "Mode": "Rotate"}},
{"Timestamp": "2020-10-30 15:05:39", "File": "Energy%203D%20ENGT%20180%20Design%20PROJECT.ng3", "Edit Window": {"Type": "Window", "Building": 2, "ID": 16, "Coordinates": [{"x": 2, "y": -25, "z": 15}, {"x": 2, "y": -25, "z": 8.6}, {"x": 8, "y": -25, "z": 15}, {"x": 8, "y": -25, "z": 8.6}]}},
{"Timestamp": "2020-10-30 15:05:39", "File": "Energy%203D%20ENGT%20180%20Design%20PROJECT.ng3", "Camera": {"Position": {"x": -61.183, "y": -70.537, "z": 35.207}, "Direction": {"x": 0.632, "y": 0.748, "z": -0.204}, "Mode": "Rotate"}},
{"Timestamp": "2020-10-30 15:05:41", "File": "Energy%203D%20ENGT%20180%20Design%20PROJECT.ng3", "Undo": "Edit Window"},
{"Timestamp": "2020-10-30 15:05:43", "File": "Energy%203D%20ENGT%20180%20Design%20PROJECT.ng3", "Camera": {"Position": {"x": 16.391, "y": -96.583, "z": 21.005}, "Direction": {"x": -0.098, "y": 0.993, "z": -0.07}, "Mode": "Rotate"}},
{"Timestamp": "2020-10-30 15:06:00", "File": "Energy%203D%20ENGT%20180%20Design%20PROJECT.ng3", "Camera": {"Position": {"x": -47.817, "y": -82.536, "z": 19.413}, "Direction": {"x": 0.506, "y": 0.861, "z": -0.055}, "Mode": "Rotate"}},
{"Timestamp": "2020-10-30 15:06:03", "File": "Energy%203D%20ENGT%20180%20Design%20PROJECT.ng3", "Camera": {"Position": {"x": -6.377, "y": -96.523, "z": 18.352}, "Direction": {"x": 0.116, "y": 0.992, "z": -0.045}, "Mode": "Rotate"}},
{"Timestamp": "2020-10-30 15:06:09", "File": "Energy%203D%20ENGT%20180%20Design%20PROJECT.ng3", "Camera": {"Position": {"x": -25.858, "y": -89.9, "z": 36.246}, "Direction": {"x": 0.3, "y": 0.93, "z": -0.213}, "Mode": "Rotate"}},
{"Timestamp": "2020-10-30 15:06:10", "File": "Energy%203D%20ENGT%20180%20Design%20PROJECT.ng3", "Camera": {"Position": {"x": -26.316, "y": -89.631, "z": 36.765}, "Direction": {"x": 0.304, "y": 0.927, "z": -0.218}, "Mode": "Rotate"}},
{"Timestamp": "2020-10-30 15:06:13", "File": "Energy%203D%20ENGT%20180%20Design%20PROJECT.ng3", "Camera": {"Position": {"x": -0.468, "y": -95.531, "z": 32.076}, "Direction": {"x": 0.061, "y": 0.983, "z": -0.174}, "Mode": "Rotate"}},
{"Timestamp": "2020-10-30 15:06:17", "File": "Energy%203D%20ENGT%20180%20Design%20PROJECT.ng3", "Camera": {"Position": {"x": -19.715, "y": -93.125, "z": 28.402}, "Direction": {"x": 0.242, "y": 0.96, "z": -0.14}, "Mode": "Rotate"}},
{"Timestamp": "2020-10-30 15:06:18", "File": "Energy%203D%20ENGT%20180%20Design%20PROJECT.ng3", "Camera": {"Position": {"x": -21.424, "y": -99.909, "z": 29.96}, "Direction": {"x": 0.242, "y": 0.96, "z": -0.144}, "Mode": "Rotate"}},
{"Timestamp": "2020-10-30 15:06:36", "File": "Energy%203D%20ENGT%20180%20Design%20PROJECT.ng3", "Add Tree": {"Species": "Dogwood", "ID": 39, "Coordinates": [{"x": -19, "y": -48, "z": 0}]}},
{"Timestamp": "2020-10-30 15:06:38", "File": "Energy%203D%20ENGT%20180%20Design%20PROJECT.ng3", "Edit Window": {"Type": "Window", "Building": 2, "ID": 15, "Coordinates": [{"x": 0, "y": -25, "z": 11}, {"x": 0, "y": -25, "z": 4.6}, {"x": 6, "y": -25, "z": 11}, {"x": 6, "y": -25, "z": 4.6}]}},
{"Timestamp": "2020-10-30 15:06:38", "File": "Energy%203D%20ENGT%20180%20Design%20PROJECT.ng3", "Camera": {"Position": {"x": -62.559, "y": -220.465, "z": 48.53}, "Direction": {"x": 0.285, "y": 0.948, "z": -0.144}, "Mode": "Rotate"}},
{"Timestamp": "2020-10-30 15:06:40", "File": "Energy%203D%20ENGT%20180%20Design%20PROJECT.ng3", "Undo": "Edit Window"},
{"Timestamp": "2020-10-30 15:06:45", "File": "Energy%203D%20ENGT%20180%20Design%20PROJECT.ng3", "Add Tree": {"Species": "Dogwood", "ID": 40, "Coordinates": [{"x": 22, "y": -48, "z": 0}]}},
{"Timestamp": "2020-10-30 15:06:49", "File": "Energy%203D%20ENGT%20180%20Design%20PROJECT.ng3", "Camera": {"Position": {"x": 230.31, "y": -48.322, "z": 50.848}, "Direction": {"x": -0.965, "y": 0.213, "z": -0.154}, "Mode": "Rotate"}},
{"Timestamp": "2020-10-30 15:06:54", "File": "Energy%203D%20ENGT%20180%20Design%20PROJECT.ng3", "Add Tree": {"Species": "Dogwood", "ID": 41, "Coordinates": [{"x": 63, "y": -14, "z": -0}]}},
{"Timestamp": "2020-10-30 15:06:59", "File": "Energy%203D%20ENGT%20180%20Design%20PROJECT.ng3", "Add Tree": {"Species": "Dogwood", "ID": 42, "Coordinates": [{"x": 60, "y": 7, "z": -0}]}},
{"Timestamp": "2020-10-30 15:07:01", "File": "Energy%203D%20ENGT%20180%20Design%20PROJECT.ng3", "Camera": {"Position": {"x": 40.883, "y": 231.491, "z": 42.721}, "Direction": {"x": -0.157, "y": -0.98, "z": -0.12}, "Mode": "Rotate"}},
{"Timestamp": "2020-10-30 15:07:11", "File": "Energy%203D%20ENGT%20180%20Design%20PROJECT.ng3", "Add Tree": {"Species": "Dogwood", "ID": 43, "Coordinates": [{"x": 19, "y": 58, "z": 0}]}},
{"Timestamp": "2020-10-30 15:07:13", "File": "Energy%203D%20ENGT%20180%20Design%20PROJECT.ng3", "Camera": {"Position": {"x": 42.054, "y": 231.441, "z": 41.557}, "Direction": {"x": -0.162, "y": -0.98, "z": -0.115}, "Mode": "Rotate"}},
{"Timestamp": "2020-10-30 15:07:14", "File": "Energy%203D%20ENGT%20180%20Design%20PROJECT.ng3", "Edit Tree": {"Species": "Dogwood", "ID": 43, "Coordinates": [{"x": 18.867, "y": 56.991, "z": 0}]}},
{"Timestamp": "2020-10-30 15:07:15", "File": "Energy%203D%20ENGT%20180%20Design%20PROJECT.ng3", "Remove Tree": {"Species": "Dogwood", "ID": 43, "Coordinates": [{"x": 18.867, "y": 56.991, "z": 0}]}},
{"Timestamp": "2020-10-30 15:07:18", "File": "Energy%203D%20ENGT%20180%20Design%20PROJECT.ng3", "Camera": {"Position": {"x": -222.859, "y": 59.458, "z": 22.862}, "Direction": {"x": 0.969, "y": -0.246, "z": -0.035}, "Mode": "Rotate"}},
{"Timestamp": "2020-10-30 15:07:21", "File": "Energy%203D%20ENGT%20180%20Design%20PROJECT.ng3", "Add Tree": {"Species": "Dogwood", "ID": 44, "Coordinates": [{"x": -47, "y": 8, "z": -0}]}},
{"Timestamp": "2020-10-30 15:07:22", "File": "Energy%203D%20ENGT%20180%20Design%20PROJECT.ng3", "Camera": {"Position": {"x": -212.064, "y": 9.079, "z": 104.863}, "Direction": {"x": 0.922, "y": -0.032, "z": -0.385}, "Mode": "Rotate"}},
{"Timestamp": "2020-10-30 15:07:24", "File": "Energy%203D%20ENGT%20180%20Design%20PROJECT.ng3", "Edit Tree": {"Species": "Dogwood", "ID": 44, "Coordinates": [{"x": -49.99, "y": 10.282, "z": -0}]}},
{"Timestamp": "2020-10-30 15:07:24", "File": "Energy%203D%20ENGT%20180%20Design%20PROJECT.ng3", "Camera": {"Position": {"x": -212.151, "y": 5.835, "z": 104.863}, "Direction": {"x": 0.923, "y": -0.018, "z": -0.385}, "Mode": "Rotate"}},
{"Timestamp": "2020-10-30 15:07:29", "File": "Energy%203D%20ENGT%20180%20Design%20PROJECT.ng3", "Add Tree": {"Species": "Dogwood", "ID": 45, "Coordinates": [{"x": -48, "y": -9, "z": 0}]}},
{"Timestamp": "2020-10-30 15:07:41", "File": "Energy%203D%20ENGT%20180%20Design%20PROJECT.ng3", "BuildingCost": [{"Foundation": 2, "Amount": 192893.023855359}]},
{"Timestamp": "2020-10-30 15:07:50", "File": "Energy%203D%20ENGT%20180%20Design%20PROJECT.ng3", "Graph Tab": "Energy"},
{"Timestamp": "2020-10-30 15:08:11", "File": "Energy%203D%20ENGT%20180%20Design%20PROJECT.ng3", "EnergyAnnualAnalysis": {"Months": 12, "Building": 2, "Net": {"Monthly": [39.27,20.64,20.64,3.89,-3.25,5.61,7.08,5.92,8.24,5.26,16.25,34.39]
, "Total": 4986.75}, "AC": {"Monthly": [0,0,0,0,8.29,24.72,35.06,32.11,25.66,8.83,0,0]
, "Total": 4096.47}, "Heater": {"Monthly": [52.92,39.94,39.94,28.17,15.8,8.85,0,0,6.4,15.92,27.35,44.01]
, "Total": 8495.18}, "Windows": {"Monthly": [15.12,20.43,20.43,23.13,20.51,21.54,22.06,20.55,17.59,14.11,8.66,11.03]
, "Total": 6544.73}, "Solar Panels": {"Monthly": [13.65,19.3,19.3,24.28,27.34,27.96,27.98,26.19,23.82,19.49,11.1,9.61]
, "Total": 7604.9}}},
{"Timestamp": "2020-10-30 15:08:36", "File": "Energy%203D%20ENGT%20180%20Design%20PROJECT.ng3", "Camera": {"Position": {"x": 113.637, "y": 195.824, "z": 87.284}, "Direction": {"x": -0.467, "y": -0.828, "z": -0.31}, "Mode": "Rotate"}},
{"Timestamp": "2020-10-30 15:08:38", "File": "Energy%203D%20ENGT%20180%20Design%20PROJECT.ng3", "Camera": {"Position": {"x": 52.729, "y": -212.264, "z": 97.237}, "Direction": {"x": -0.207, "y": 0.913, "z": -0.352}, "Mode": "Rotate"}},
{"Timestamp": "2020-10-30 15:08:48", "File": "Energy%203D%20ENGT%20180%20Design%20PROJECT.ng3", "Change Thickness for All Walls": {"New Value": 2.0}},
{"Timestamp": "2020-10-30 15:08:57", "File": "Energy%203D%20ENGT%20180%20Design%20PROJECT.ng3", "Camera": {"Position": {"x": -36.258, "y": -218.228, "z": 85.052}, "Direction": {"x": 0.172, "y": 0.938, "z": -0.3}, "Mode": "Rotate"}},
{"Timestamp": "2020-10-30 15:08:59", "File": "Energy%203D%20ENGT%20180%20Design%20PROJECT.ng3", "Change Date": {"Old Date": "10/30", "New Date": "12/1"}},
{"Timestamp": "2020-10-30 15:09:03", "File": "Energy%203D%20ENGT%20180%20Design%20PROJECT.ng3", "Change Date": {"Old Date": "10/1", "New Date": "10/30"}},
{"Timestamp": "2020-10-30 15:09:08", "File": "Energy%203D%20ENGT%20180%20Design%20PROJECT.ng3", "Camera": {"Position": {"x": -97.35, "y": -187.824, "z": 108.098}, "Direction": {"x": 0.433, "y": 0.808, "z": -0.399}, "Mode": "Rotate"}},
{"Timestamp": "2020-10-30 15:09:10", "File": "Energy%203D%20ENGT%20180%20Design%20PROJECT.ng3", "Camera": {"Position": {"x": 131.318, "y": -177.104, "z": 97.237}, "Direction": {"x": -0.542, "y": 0.763, "z": -0.352}, "Mode": "Rotate"}},
{"Timestamp": "2020-10-30 15:09:13", "File": "Energy%203D%20ENGT%20180%20Design%20PROJECT.ng3", "Camera": {"Position": {"x": -77.146, "y": -203.808, "z": 92.833}, "Direction": {"x": 0.347, "y": 0.877, "z": -0.333}, "Mode": "Rotate"}},
{"Timestamp": "2020-10-30 15:09:16", "File": "Energy%203D%20ENGT%20180%20Design%20PROJECT.ng3", "Camera": {"Position": {"x": 6.004, "y": -222.255, "z": 83.933}, "Direction": {"x": -0.008, "y": 0.955, "z": -0.295}, "Mode": "Rotate"}},
{"Timestamp": "2020-10-30 15:09:18", "File": "Energy%203D%20ENGT%20180%20Design%20PROJECT.ng3", "Camera": {"Position": {"x": 78.117, "y": -208.574, "z": 87.284}, "Direction": {"x": -0.315, "y": 0.897, "z": -0.31}, "Mode": "Rotate"}},
{"Timestamp": "2020-10-30 15:09:46", "File": "Energy%203D%20ENGT%20180%20Design%20PROJECT.ng3", "Remove Tree": {"Species": "Dogwood", "ID": 50, "Coordinates": [{"x": -37, "y": 407, "z": 0}]}},
{"Timestamp": "2020-10-30 15:09:52", "File": "Energy%203D%20ENGT%20180%20Design%20PROJECT.ng3", "Add Mirror": {"Type": "Mirror", "Building": 2, "ID": 51, "Coordinates": [{"x": 40, "y": 8, "z": 11}]}},
{"Timestamp": "2020-10-30 15:09:53", "File": "Energy%203D%20ENGT%20180%20Design%20PROJECT.ng3", "Camera": {"Position": {"x": 80.215, "y": -207.824, "z": 87.284}, "Direction": {"x": -0.324, "y": 0.894, "z": -0.31}, "Mode": "Rotate"}},
{"Timestamp": "2020-10-30 15:09:54", "File": "Energy%203D%20ENGT%20180%20Design%20PROJECT.ng3", "Camera": {"Position": {"x": 106.845, "y": 212.395, "z": 12.315}, "Direction": {"x": -0.438, "y": -0.899, "z": 0.01}, "Mode": "Rotate"}},
{"Timestamp": "2020-10-30 15:09:56", "File": "Energy%203D%20ENGT%20180%20Design%20PROJECT.ng3", "Camera": {"Position": {"x": 85.662, "y": 198.022, "z": 113.443}, "Direction": {"x": -0.348, "y": -0.838, "z": -0.421}, "Mode": "Rotate"}},
{"Timestamp": "2020-10-30 15:10:01", "File": "Energy%203D%20ENGT%20180%20Design%20PROJECT.ng3", "Graph Tab": "Cost"},
{"Timestamp": "2020-10-30 15:10:02", "File": "Energy%203D%20ENGT%20180%20Design%20PROJECT.ng3", "Graph Tab": "Basics"},
{"Timestamp": "2020-10-30 15:10:03", "File": "Energy%203D%20ENGT%20180%20Design%20PROJECT.ng3", "Graph Tab": "Cost"},
{"Timestamp": "2020-10-30 15:10:06", "File": "Energy%203D%20ENGT%20180%20Design%20PROJECT.ng3", "Camera": {"Position": {"x": 85.471, "y": 197.564, "z": 114.505}, "Direction": {"x": -0.347, "y": -0.836, "z": -0.426}, "Mode": "Rotate"}},
{"Timestamp": "2020-10-30 15:10:07", "File": "Energy%203D%20ENGT%20180%20Design%20PROJECT.ng3", "Remove Mirror": {"Type": "Mirror", "Building": 2, "ID": 51, "Coordinates": [{"x": 40, "y": 8, "z": 11}]}},
{"Timestamp": "2020-10-30 15:10:28", "File": "Energy%203D%20ENGT%20180%20Design%20PROJECT.ng3", "Camera": {"Position": {"x": -54.688, "y": -213.659, "z": 86.169}, "Direction": {"x": 0.251, "y": 0.919, "z": -0.305}, "Mode": "Rotate"}},
{"Timestamp": "2020-10-30 15:10:31", "File": "Energy%203D%20ENGT%20180%20Design%20PROJECT.ng3", "Camera": {"Position": {"x": -123.165, "y": -189.817, "z": 60.081}, "Direction": {"x": 0.543, "y": 0.817, "z": -0.194}, "Mode": "Rotate"}},
{"Timestamp": "2020-10-30 15:10:32", "File": "Energy%203D%20ENGT%20180%20Design%20PROJECT.ng3", "Undo": "Remove Mirror"},
{"Timestamp": "2020-10-30 15:10:34", "File": "Energy%203D%20ENGT%20180%20Design%20PROJECT.ng3", "Camera": {"Position": {"x": 98.201, "y": -188.975, "z": 113.443}, "Direction": {"x": -0.401, "y": 0.813, "z": -0.421}, "Mode": "Rotate"}},
{"Timestamp": "2020-10-30 15:10:37", "File": "Energy%203D%20ENGT%20180%20Design%20PROJECT.ng3", "Remove Mirror": {"Type": "Mirror", "Building": 2, "ID": 51, "Coordinates": [{"x": 40, "y": 8, "z": 11}]}},
{"Timestamp": "2020-10-30 15:11:05", "File": "Energy%203D%20ENGT%20180%20Design%20PROJECT.ng3", "Add ParabolicTrough": {"Type": "ParabolicTrough", "Building": 2, "ID": 55, "Coordinates": [{"x": 31.5, "y": -8, "z": 16}]}},
{"Timestamp": "2020-10-30 15:11:09", "File": "Energy%203D%20ENGT%20180%20Design%20PROJECT.ng3", "Camera": {"Position": {"x": -53.422, "y": -213.249, "z": 88.397}, "Direction": {"x": 0.246, "y": 0.917, "z": -0.315}, "Mode": "Rotate"}},
{"Timestamp": "2020-10-30 15:11:19", "File": "Energy%203D%20ENGT%20180%20Design%20PROJECT.ng3", "Add ParabolicTrough": {"Type": "ParabolicTrough", "Building": 2, "ID": 56, "Coordinates": [{"x": -29.5, "y": 22.5, "z": 16}]}},
{"Timestamp": "2020-10-30 15:11:59", "File": "Energy%203D%20ENGT%20180%20Design%20PROJECT.ng3", "Add ParabolicTrough": {"Type": "ParabolicTrough", "Building": 2, "ID": 57, "Coordinates": [{"x": -16, "y": -4.5, "z": 16}]}},
{"Timestamp": "2020-10-30 15:12:06", "File": "Energy%203D%20ENGT%20180%20Design%20PROJECT.ng3", "Camera": {"Position": {"x": -141.611, "y": -181.645, "z": 24.033}, "Direction": {"x": 0.622, "y": 0.782, "z": -0.04}, "Mode": "Rotate"}},
{"Timestamp": "2020-10-30 15:12:10", "File": "Energy%203D%20ENGT%20180%20Design%20PROJECT.ng3", "Camera": {"Position": {"x": -141.638, "y": -181.679, "z": 22.862}, "Direction": {"x": 0.622, "y": 0.782, "z": -0.035}, "Mode": "Rotate"}},
{"Timestamp": "2020-10-30 15:12:18", "File": "Energy%203D%20ENGT%20180%20Design%20PROJECT.ng3", "Change Height for All Walls on Selected Foundation": {"Foundation": 2, "New Value": 22.5}},
{"Timestamp": "2020-10-30 15:12:23", "File": "Energy%203D%20ENGT%20180%20Design%20PROJECT.ng3", "Camera": {"Position": {"x": -85.972, "y": -213.436, "z": 38.062}, "Direction": {"x": 0.385, "y": 0.918, "z": -0.1}, "Mode": "Rotate"}},
{"Timestamp": "2020-10-30 15:12:30", "File": "Energy%203D%20ENGT%20180%20Design%20PROJECT.ng3", "Camera": {"Position": {"x": -86.061, "y": -202.116, "z": 87.284}, "Direction": {"x": 0.385, "y": 0.869, "z": -0.31}, "Mode": "Rotate"}},
{"Timestamp": "2020-10-30 15:12:32", "File": "Energy%203D%20ENGT%20180%20Design%20PROJECT.ng3", "Camera": {"Position": {"x": -16.055, "y": -217.99, "z": 93.937}, "Direction": {"x": 0.086, "y": 0.937, "z": -0.338}, "Mode": "Rotate"}},
{"Timestamp": "2020-10-30 15:12:42", "File": "Energy%203D%20ENGT%20180%20Design%20PROJECT.ng3", "Add SolarPanel": {"Type": "SolarPanel", "Building": 2, "ID": 59, "Coordinates": [{"x": -12.23, "y": -11.635, "z": 28.113}]}},
{"Timestamp": "2020-10-30 15:12:43", "File": "Energy%203D%20ENGT%20180%20Design%20PROJECT.ng3", "Camera": {"Position": {"x": 26.768, "y": -216.539, "z": 97.237}, "Direction": {"x": -0.096, "y": 0.931, "z": -0.352}, "Mode": "Rotate"}},
{"Timestamp": "2020-10-30 15:12:45", "File": "Energy%203D%20ENGT%20180%20Design%20PROJECT.ng3", "Camera": {"Position": {"x": 26.768, "y": -216.539, "z": 107.151}, "Direction": {"x": -0.096, "y": 0.931, "z": -0.352}, "Mode": "Zoom"}},
{"Timestamp": "2020-10-30 15:12:46", "File": "Energy%203D%20ENGT%20180%20Design%20PROJECT.ng3", "Camera": {"Position": {"x": 34.844, "y": -294.526, "z": 126.746}, "Direction": {"x": -0.096, "y": 0.931, "z": -0.352}, "Mode": "Zoom"}},
{"Timestamp": "2020-10-30 15:12:46", "File": "Energy%203D%20ENGT%20180%20Design%20PROJECT.ng3", "Camera": {"Position": {"x": 31.383, "y": -261.099, "z": 114.098}, "Direction": {"x": -0.096, "y": 0.931, "z": -0.352}, "Mode": "Zoom"}},
{"Timestamp": "2020-10-30 15:12:47", "File": "Energy%203D%20ENGT%20180%20Design%20PROJECT.ng3", "Camera": {"Position": {"x": 28.378, "y": -232.083, "z": 103.118}, "Direction": {"x": -0.096, "y": 0.931, "z": -0.352}, "Mode": "Zoom"}},
{"Timestamp": "2020-10-30 15:12:47", "File": "Energy%203D%20ENGT%20180%20Design%20PROJECT.ng3", "Camera": {"Position": {"x": 23.755, "y": -187.436, "z": 86.224}, "Direction": {"x": -0.096, "y": 0.931, "z": -0.352}, "Mode": "Zoom"}},
{"Timestamp": "2020-10-30 15:12:51", "File": "Energy%203D%20ENGT%20180%20Design%20PROJECT.ng3", "Edit SolarPanel": {"Type": "SolarPanel", "Building": 2, "ID": 59, "Coordinates": [{"x": -12.725, "y": -12.13, "z": 27.884}]}},
{"Timestamp": "2020-10-30 15:12:51", "File": "Energy%203D%20ENGT%20180%20Design%20PROJECT.ng3", "Camera": {"Position": {"x": 17.453, "y": -126.577, "z": 63.196}, "Direction": {"x": -0.096, "y": 0.931, "z": -0.352}, "Mode": "Rotate"}},
{"Timestamp": "2020-10-30 15:12:57", "File": "Energy%203D%20ENGT%20180%20Design%20PROJECT.ng3", "Change Azimuth": {"Foundation": 2, "ID": 59, "Old Value": 0.0, "New Value": 355.0}},
{"Timestamp": "2020-10-30 15:12:59", "File": "Energy%203D%20ENGT%20180%20Design%20PROJECT.ng3", "Camera": {"Position": {"x": 16.789, "y": -126.644, "z": 63.196}, "Direction": {"x": -0.092, "y": 0.931, "z": -0.352}, "Mode": "Rotate"}},
{"Timestamp": "2020-10-30 15:13:00", "File": "Energy%203D%20ENGT%20180%20Design%20PROJECT.ng3", "Camera": {"Position": {"x": 16.148, "y": -126.956, "z": 62.528}, "Direction": {"x": -0.087, "y": 0.934, "z": -0.348}, "Mode": "Rotate"}},
{"Timestamp": "2020-10-30 15:13:02", "File": "Energy%203D%20ENGT%20180%20Design%20PROJECT.ng3", "Change Azimuth": {"Foundation": 2, "ID": 59, "Old Value": 355.0, "New Value": 350.0}},
{"Timestamp": "2020-10-30 15:13:05", "File": "Energy%203D%20ENGT%20180%20Design%20PROJECT.ng3", "Camera": {"Position": {"x": 12.135, "y": -127.021, "z": 63.196}, "Direction": {"x": -0.059, "y": 0.934, "z": -0.352}, "Mode": "Rotate"}},
{"Timestamp": "2020-10-30 15:13:14", "File": "Energy%203D%20ENGT%20180%20Design%20PROJECT.ng3", "Rotate Solar Panel": {"Foundation": 2, "ID": 59, "New Value": false}},
{"Timestamp": "2020-10-30 15:13:24", "File": "Energy%203D%20ENGT%20180%20Design%20PROJECT.ng3", "Edit SolarPanel": {"Type": "SolarPanel", "Building": 2, "ID": 59, "Coordinates": [{"x": -19.16, "y": -12.625, "z": 27.655}]}},
{"Timestamp": "2020-10-30 15:13:24", "File": "Energy%203D%20ENGT%20180%20Design%20PROJECT.ng3", "Camera": {"Position": {"x": 14.071, "y": -126.114, "z": 65.191}, "Direction": {"x": -0.073, "y": 0.928, "z": -0.366}, "Mode": "Rotate"}},
{"Timestamp": "2020-10-30 15:13:26", "File": "Energy%203D%20ENGT%20180%20Design%20PROJECT.ng3", "Camera": {"Position": {"x": 14.051, "y": -125.852, "z": 65.854}, "Direction": {"x": -0.073, "y": 0.926, "z": -0.371}, "Mode": "Rotate"}},
{"Timestamp": "2020-10-30 15:13:33", "File": "Energy%203D%20ENGT%20180%20Design%20PROJECT.ng3", "Camera": {"Position": {"x": 14.03, "y": -125.586, "z": 66.515}, "Direction": {"x": -0.072, "y": 0.924, "z": -0.376}, "Mode": "Rotate"}},
{"Timestamp": "2020-10-30 15:13:44", "File": "Energy%203D%20ENGT%20180%20Design%20PROJECT.ng3", "BuildingCost": {"Foundation": 2, "Amount": 184227.0685241664}},
{"Timestamp": "2020-10-30 15:13:45", "File": "Energy%203D%20ENGT%20180%20Design%20PROJECT.ng3", "Camera": {"Position": {"x": 14.051, "y": -125.852, "z": 65.854}, "Direction": {"x": -0.073, "y": 0.926, "z": -0.371}, "Mode": "Rotate"}},
{"Timestamp": "2020-10-30 15:13:54", "File": "Energy%203D%20ENGT%20180%20Design%20PROJECT.ng3", "Camera": {"Position": {"x": 14.732, "y": -126.06, "z": 65.191}, "Direction": {"x": -0.077, "y": 0.927, "z": -0.366}, "Mode": "Rotate"}},
{"Timestamp": "2020-10-30 15:13:56", "File": "Energy%203D%20ENGT%20180%20Design%20PROJECT.ng3", "Camera": {"Position": {"x": 14.71, "y": -125.798, "z": 65.854}, "Direction": {"x": -0.077, "y": 0.925, "z": -0.371}, "Mode": "Rotate"}},
{"Timestamp": "2020-10-30 15:14:05", "File": "Energy%203D%20ENGT%20180%20Design%20PROJECT.ng3", "Add SolarPanel": {"Type": "SolarPanel", "Building": 2, "ID": 62, "Coordinates": [{"x": -9.26, "y": -11.635, "z": 28.113}]}},
{"Timestamp": "2020-10-30 15:14:12", "File": "Energy%203D%20ENGT%20180%20Design%20PROJECT.ng3", "Rotate Solar Panel": {"Foundation": 2, "ID": 62, "New Value": false}},
{"Timestamp": "2020-10-30 15:14:16", "File": "Energy%203D%20ENGT%20180%20Design%20PROJECT.ng3", "Edit SolarPanel": {"Type": "SolarPanel", "Building": 2, "ID": 62, "Coordinates": [{"x": -9.26, "y": -12.625, "z": 27.655}]}},
{"Timestamp": "2020-10-30 15:14:21", "File": "Energy%203D%20ENGT%20180%20Design%20PROJECT.ng3", "Add SolarPanel": {"Type": "SolarPanel", "Building": 2, "ID": 63, "Coordinates": [{"x": 1.135, "y": -12.13, "z": 27.884}]}},
{"Timestamp": "2020-10-30 15:14:24", "File": "Energy%203D%20ENGT%20180%20Design%20PROJECT.ng3", "Camera": {"Position": {"x": 14.679, "y": -125.42, "z": 66.805}, "Direction": {"x": -0.077, "y": 0.925, "z": -0.371}, "Mode": "Pan"}},
{"Timestamp": "2020-10-30 15:14:26", "File": "Energy%203D%20ENGT%20180%20Design%20PROJECT.ng3", "Camera": {"Position": {"x": 13.987, "y": -125.094, "z": 67.757}, "Direction": {"x": -0.073, "y": 0.926, "z": -0.371}, "Mode": "Rotate"}},
{"Timestamp": "2020-10-30 15:14:33", "File": "Energy%203D%20ENGT%20180%20Design%20PROJECT.ng3", "Rotate Solar Panel": {"Foundation": 2, "ID": 63, "New Value": false}},
{"Timestamp": "2020-10-30 15:14:44", "File": "Energy%203D%20ENGT%20180%20Design%20PROJECT.ng3", "Edit SolarPanel": {"Type": "SolarPanel", "Building": 2, "ID": 63, "Coordinates": [{"x": 0.64, "y": -12.625, "z": 27.655}]}},
{"Timestamp": "2020-10-30 15:14:44", "File": "Energy%203D%20ENGT%20180%20Design%20PROJECT.ng3", "Camera": {"Position": {"x": 13.308, "y": -124.879, "z": 68.418}, "Direction": {"x": -0.068, "y": 0.924, "z": -0.376}, "Mode": "Rotate"}},
{"Timestamp": "2020-10-30 15:14:51", "File": "Energy%203D%20ENGT%20180%20Design%20PROJECT.ng3", "Add SolarPanel": {"Type": "SolarPanel", "Building": 2, "ID": 64, "Coordinates": [{"x": 11.035, "y": -12.13, "z": 27.884}]}},
{"Timestamp": "2020-10-30 15:14:52", "File": "Energy%203D%20ENGT%20180%20Design%20PROJECT.ng3", "Camera": {"Position": {"x": 13.786, "y": -124.458, "z": 69.369}, "Direction": {"x": -0.068, "y": 0.924, "z": -0.376}, "Mode": "Pan"}},
{"Timestamp": "2020-10-30 15:14:57", "File": "Energy%203D%20ENGT%20180%20Design%20PROJECT.ng3", "Camera": {"Position": {"x": 15.249, "y": -123.577, "z": 71.273}, "Direction": {"x": -0.068, "y": 0.924, "z": -0.376}, "Mode": "Pan"}},
{"Timestamp": "2020-10-30 15:15:01", "File": "Energy%203D%20ENGT%20180%20Design%20PROJECT.ng3", "Camera": {"Position": {"x": 14.713, "y": -123.229, "z": 72.227}, "Direction": {"x": -0.068, "y": 0.924, "z": -0.376}, "Mode": "Pan"}},
{"Timestamp": "2020-10-30 15:15:04", "File": "Energy%203D%20ENGT%20180%20Design%20PROJECT.ng3", "Camera": {"Position": {"x": 15.4, "y": -123.565, "z": 71.272}, "Direction": {"x": -0.072, "y": 0.924, "z": -0.376}, "Mode": "Rotate"}},
{"Timestamp": "2020-10-30 15:15:06", "File": "Energy%203D%20ENGT%20180%20Design%20PROJECT.ng3", "Camera": {"Position": {"x": 15.379, "y": -123.296, "z": 71.932}, "Direction": {"x": -0.072, "y": 0.922, "z": -0.38}, "Mode": "Rotate"}},
{"Timestamp": "2020-10-30 15:15:07", "File": "Energy%203D%20ENGT%20180%20Design%20PROJECT.ng3", "Camera": {"Position": {"x": 14.841, "y": -122.945, "z": 72.885}, "Direction": {"x": -0.072, "y": 0.922, "z": -0.38}, "Mode": "Pan"}},
{"Timestamp": "2020-10-30 15:15:11", "File": "Energy%203D%20ENGT%20180%20Design%20PROJECT.ng3", "Camera": {"Position": {"x": 14.841, "y": -122.555, "z": 73.838}, "Direction": {"x": -0.072, "y": 0.922, "z": -0.38}, "Mode": "Pan"}},
{"Timestamp": "2020-10-30 15:15:13", "File": "Energy%203D%20ENGT%20180%20Design%20PROJECT.ng3", "Camera": {"Position": {"x": 14.81, "y": -122.555, "z": 73.838}, "Direction": {"x": -0.072, "y": 0.922, "z": -0.38}, "Mode": "Pan"}},
{"Timestamp": "2020-10-30 15:15:17", "File": "Energy%203D%20ENGT%20180%20Design%20PROJECT.ng3", "Camera": {"Position": {"x": 13.793, "y": -122.634, "z": 73.838}, "Direction": {"x": -0.072, "y": 0.922, "z": -0.38}, "Mode": "Pan"}},
{"Timestamp": "2020-10-30 15:15:20", "File": "Energy%203D%20ENGT%20180%20Design%20PROJECT.ng3", "Camera": {"Position": {"x": 13.793, "y": -122.986, "z": 72.884}, "Direction": {"x": -0.072, "y": 0.922, "z": -0.38}, "Mode": "Pan"}},
{"Timestamp": "2020-10-30 15:15:25", "File": "Energy%203D%20ENGT%20180%20Design%20PROJECT.ng3", "Camera": {"Position": {"x": 14.332, "y": -123.376, "z": 71.931}, "Direction": {"x": -0.072, "y": 0.922, "z": -0.38}, "Mode": "Pan"}},
{"Timestamp": "2020-10-30 15:15:31", "File": "Energy%203D%20ENGT%20180%20Design%20PROJECT.ng3", "Rotate Solar Panel": {"Foundation": 2, "ID": 64, "New Value": false}},
{"Timestamp": "2020-10-30 15:15:34", "File": "Energy%203D%20ENGT%20180%20Design%20PROJECT.ng3", "Edit SolarPanel": {"Type": "SolarPanel", "Building": 2, "ID": 64, "Coordinates": [{"x": 11.035, "y": -12.625, "z": 27.655}]}},
{"Timestamp": "2020-10-30 15:15:34", "File": "Energy%203D%20ENGT%20180%20Design%20PROJECT.ng3", "Camera": {"Position": {"x": 14.362, "y": -123.376, "z": 71.931}, "Direction": {"x": -0.072, "y": 0.922, "z": -0.38}, "Mode": "Rotate"}},
{"Timestamp": "2020-10-30 15:15:35", "File": "Energy%203D%20ENGT%20180%20Design%20PROJECT.ng3", "Camera": {"Position": {"x": 15.02, "y": -123.323, "z": 71.931}, "Direction": {"x": -0.077, "y": 0.922, "z": -0.38}, "Mode": "Rotate"}},
{"Timestamp": "2020-10-30 15:15:42", "File": "Energy%203D%20ENGT%20180%20Design%20PROJECT.ng3", "Add SolarPanel": {"Type": "SolarPanel", "Building": 2, "ID": 65, "Coordinates": [{"x": 20.935, "y": -11.635, "z": 28.113}]}},
{"Timestamp": "2020-10-30 15:15:51", "File": "Energy%203D%20ENGT%20180%20Design%20PROJECT.ng3", "Rotate Solar Panel": {"Foundation": 2, "ID": 65, "New Value": false}},
{"Timestamp": "2020-10-30 15:15:54", "File": "Energy%203D%20ENGT%20180%20Design%20PROJECT.ng3", "Edit SolarPanel": {"Type": "SolarPanel", "Building": 2, "ID": 65, "Coordinates": [{"x": 20.935, "y": -12.625, "z": 27.655}]}},
{"Timestamp": "2020-10-30 15:15:54", "File": "Energy%203D%20ENGT%20180%20Design%20PROJECT.ng3", "Camera": {"Position": {"x": 15.042, "y": -123.592, "z": 71.271}, "Direction": {"x": -0.077, "y": 0.924, "z": -0.376}, "Mode": "Rotate"}},
{"Timestamp": "2020-10-30 15:16:05", "File": "Energy%203D%20ENGT%20180%20Design%20PROJECT.ng3", "BuildingCost": {"Foundation": 2, "Amount": 188307.0685241664}},
{"Timestamp": "2020-10-30 15:16:08", "File": "Energy%203D%20ENGT%20180%20Design%20PROJECT.ng3", "Camera": {"Position": {"x": 79.602, "y": -101.594, "z": 68.618}, "Direction": {"x": -0.53, "y": 0.769, "z": -0.357}, "Mode": "Rotate"}},
{"Timestamp": "2020-10-30 15:16:19", "File": "Energy%203D%20ENGT%20180%20Design%20PROJECT.ng3", "Add Rack": {"Type": "Rack", "Building": 2, "ID": 66, "Coordinates": [{"x": 35.537, "y": 0.162, "z": 25.09}]}},
{"Timestamp": "2020-10-30 15:16:22", "File": "Energy%203D%20ENGT%20180%20Design%20PROJECT.ng3", "Camera": {"Position": {"x": -100.655, "y": -79.955, "z": 57.814}, "Direction": {"x": 0.735, "y": 0.617, "z": -0.281}, "Mode": "Rotate"}},
{"Timestamp": "2020-10-30 15:16:34", "File": "Energy%203D%20ENGT%20180%20Design%20PROJECT.ng3", "Add Rack": {"Type": "Rack", "Building": 2, "ID": 68, "Coordinates": [{"x": -30.463, "y": -1.075, "z": 25.138}]}},
{"Timestamp": "2020-10-30 15:16:36", "File": "Energy%203D%20ENGT%20180%20Design%20PROJECT.ng3", "Camera": {"Position": {"x": -102.634, "y": -1.991, "z": 111.73}, "Direction": {"x": 0.749, "y": 0.071, "z": -0.659}, "Mode": "Rotate"}},
{"Timestamp": "2020-10-30 15:16:37", "File": "Energy%203D%20ENGT%20180%20Design%20PROJECT.ng3", "Camera": {"Position": {"x": -102.113, "y": -2.477, "z": 112.265}, "Direction": {"x": 0.745, "y": 0.074, "z": -0.663}, "Mode": "Rotate"}},
{"Timestamp": "2020-10-30 15:16:41", "File": "Energy%203D%20ENGT%20180%20Design%20PROJECT.ng3", "Camera": {"Position": {"x": -101.29, "y": -8.825, "z": 112.265}, "Direction": {"x": 0.739, "y": 0.118, "z": -0.663}, "Mode": "Rotate"}},
{"Timestamp": "2020-10-30 15:16:49", "File": "Energy%203D%20ENGT%20180%20Design%20PROJECT.ng3", "Edit Rack": {"Type": "Rack", "Building": 2, "ID": 68, "Coordinates": [{"x": -30.463, "y": 0.162, "z": 25.138}]}},
{"Timestamp": "2020-10-30 15:16:49", "File": "Energy%203D%20ENGT%20180%20Design%20PROJECT.ng3", "Camera": {"Position": {"x": -101.204, "y": -9.352, "z": 112.265}, "Direction": {"x": 0.738, "y": 0.122, "z": -0.663}, "Mode": "Rotate"}},
{"Timestamp": "2020-10-30 15:16:53", "File": "Energy%203D%20ENGT%20180%20Design%20PROJECT.ng3", "Camera": {"Position": {"x": -38.746, "y": -97.031, "z": 104.004}, "Direction": {"x": 0.3, "y": 0.737, "z": -0.605}, "Mode": "Rotate"}},
{"Timestamp": "2020-10-30 15:16:56", "File": "Energy%203D%20ENGT%20180%20Design%20PROJECT.ng3", "BuildingCost": [{"Foundation": 2, "Amount": 198507.0685241664}]},
{"Timestamp": "2020-10-30 15:16:59", "File": "Energy%203D%20ENGT%20180%20Design%20PROJECT.ng3", "Camera": {"Position": {"x": 29.325, "y": -121.059, "z": 72.589}, "Direction": {"x": -0.177, "y": 0.906, "z": -0.385}, "Mode": "Rotate"}},
{"Timestamp": "2020-10-30 15:17:06", "File": "Energy%203D%20ENGT%20180%20Design%20PROJECT.ng3", "Graph Tab": "Energy"},
{"Timestamp": "2020-10-30 15:17:38", "File": "Energy%203D%20ENGT%20180%20Design%20PROJECT.ng3", "EnergyAnnualAnalysis": {"Months": 12, "Building": 2, "Net": {"Monthly": [27.26,5.46,5.46,-14.5,-20.45,-14.16,-13.29,-12.61,-7.82,-6.68,8.93,25.54]
, "Total": -513.18}, "AC": {"Monthly": [0,0,0,0,8.28,22.61,31.7,28.99,23.26,8.25,0,0]
, "Total": 3743.97}, "Heater": {"Monthly": [48.66,36.53,36.53,25.75,14.43,8.08,0,0,5.83,14.52,24.94,40.44]
, "Total": 7777.99}, "Windows": {"Monthly": [13.37,18.15,18.15,20.54,18.07,18.92,19.35,18.13,15.51,12.61,7.79,9.74]
, "Total": 5789.61}, "Solar Panels": {"Monthly": [21.4,31.08,31.08,40.25,43.16,44.86,44.99,41.6,36.91,29.45,16.01,14.9]
, "Total": 12035.14}}},
{"Timestamp": "2020-10-30 15:19:18", "File": "Energy%203D%20ENGT%20180%20Design%20PROJECT.ng3", "Camera": {"Position": {"x": -70.296, "y": -104.983, "z": 62.576}, "Direction": {"x": 0.522, "y": 0.793, "z": -0.315}, "Mode": "Rotate"}},
{"Timestamp": "2020-10-30 15:20:57", "File": "Energy%203D%20ENGT%20180%20Design%20PROJECT.ng3", "Camera": {"Position": {"x": 19.515, "y": -127.857, "z": 57.814}, "Direction": {"x": -0.108, "y": 0.954, "z": -0.281}, "Mode": "Rotate"}},
{"Timestamp": "2020-10-30 15:22:23", "File": "Designproject_X_ENGT180.ng3", "Save": "file:/W:/ENGT%20180/Designproject_X_ENGT180.ng3*"},
{"Timestamp": "2020-10-30 15:26:29", "File": "Designproject_X_ENGT180.ng3", "Save": "file:/C:/Users/X/OneDrive/Designproject_X_ENGT180.ng3*"}