{
"Version": "8.7.4","Activities": [
{"Timestamp": "2020-10-28 14:56:33", "File": "Design%20Project%20Part%202.ng3", "Show Annotation": false},
{"Timestamp": "2020-10-28 14:56:35", "File": "Design%20Project%20Part%202.ng3", "Camera": {"Position": {"x": 110.403, "y": -15.085, "z": 40.042}, "Direction": {"x": -0.932, "y": 0.127, "z": -0.338}, "Mode": "Rotate"}},
{"Timestamp": "2020-10-28 14:56:36", "File": "Design%20Project%20Part%202.ng3", "Camera": {"Position": {"x": -25.915, "y": 106.635, "z": 44.466}, "Direction": {"x": 0.219, "y": -0.901, "z": -0.376}, "Mode": "Rotate"}},
{"Timestamp": "2020-10-28 14:56:37", "File": "Design%20Project%20Part%202.ng3", "Camera": {"Position": {"x": -43.011, "y": -99.454, "z": 47.738}, "Direction": {"x": 0.363, "y": 0.84, "z": -0.403}, "Mode": "Rotate"}},
{"Timestamp": "2020-10-28 14:56:38", "File": "Design%20Project%20Part%202.ng3", "Graph Tab": "Cost"},
{"Timestamp": "2020-10-28 14:56:44", "File": "Design%20Project%20Part%202.ng3", "Camera": {"Position": {"x": -38.695, "y": -88.259, "z": 68.796}, "Direction": {"x": 0.327, "y": 0.745, "z": -0.581}, "Mode": "Rotate"}},
{"Timestamp": "2020-10-28 14:56:45", "File": "Design%20Project%20Part%202.ng3", "Camera": {"Position": {"x": -44.242, "y": -103.72, "z": 36.118}, "Direction": {"x": 0.374, "y": 0.876, "z": -0.305}, "Mode": "Rotate"}},
{"Timestamp": "2020-10-28 14:56:46", "File": "Design%20Project%20Part%202.ng3", "Camera": {"Position": {"x": -43.723, "y": -103.94, "z": 36.118}, "Direction": {"x": 0.369, "y": 0.878, "z": -0.305}, "Mode": "Rotate"}},
{"Timestamp": "2020-10-28 14:56:47", "File": "Design%20Project%20Part%202.ng3", "Graph Tab": "Basics"},
{"Timestamp": "2020-10-28 15:05:04", "File": "Design%20Project%20Part%202.ng3", "Camera": {"Position": {"x": -44.422, "y": -105.601, "z": 36.695}, "Direction": {"x": 0.369, "y": 0.878, "z": -0.305}, "Mode": "Zoom"}},
{"Timestamp": "2020-10-28 15:05:06", "File": "Design%20Project%20Part%202.ng3", "Camera": {"Position": {"x": -40.002, "y": -105.256, "z": 55.085}, "Direction": {"x": 0.319, "y": 0.84, "z": -0.439}, "Mode": "Rotate"}},
{"Timestamp": "2020-10-28 15:05:14", "File": "Design%20Project%20Part%202.ng3", "Graph Tab": "Energy"},
{"Timestamp": "2020-10-28 15:05:18", "File": "Design%20Project%20Part%202.ng3", "EnergyAnnualAnalysis": {"Months": 12, "Building": 2, "Net": {"Monthly": [54.72,45.12,31.7,19.88,45.52,44.82,51.95,56.71,60.02,29.65,42.91,55.73]
, "Total": 16386.67}, "AC": {"Monthly": [0,0,0,0,35.84,44.82,51.95,56.71,44.14,0,0,0]
, "Total": 7101.08}, "Heater": {"Monthly": [54.72,45.12,31.7,19.88,9.68,0,0,0,15.88,29.65,42.91,55.73]
, "Total": 9285.59}, "Windows": {"Monthly": [38.43,37.95,39.15,33.9,31.66,31.93,39.2,49.13,56.27,55.06,32.46,29.14]
, "Total": 14426.23}, "Solar Panels": {"Monthly": [0,0,0,0,0,0,0,0,0,0,0,0]
, "Total": 0}}},
{"Timestamp": "2020-10-28 15:05:54", "File": "Design%20Project%20Part%202.ng3", "Camera": {"Position": {"x": -8.935, "y": -121.867, "z": 27.964}, "Direction": {"x": 0.071, "y": 0.972, "z": -0.223}, "Mode": "Rotate"}},
{"Timestamp": "2020-10-28 15:05:57", "File": "Design%20Project%20Part%202.ng3", "Graph Tab": "Cost"},
{"Timestamp": "2020-10-28 15:06:02", "File": "Design%20Project%20Part%202.ng3", "Camera": {"Position": {"x": -6.748, "y": -106.655, "z": 65.518}, "Direction": {"x": 0.054, "y": 0.851, "z": -0.523}, "Mode": "Rotate"}},
{"Timestamp": "2020-10-28 15:06:04", "File": "Design%20Project%20Part%202.ng3", "Camera": {"Position": {"x": -8.852, "y": -106.17, "z": 66.052}, "Direction": {"x": 0.071, "y": 0.847, "z": -0.527}, "Mode": "Rotate"}},
{"Timestamp": "2020-10-28 15:06:06", "File": "Design%20Project%20Part%202.ng3", "Camera": {"Position": {"x": -8.877, "y": -31.082, "z": 121.113}, "Direction": {"x": 0.071, "y": 0.248, "z": -0.966}, "Mode": "Rotate"}},
{"Timestamp": "2020-10-28 15:06:07", "File": "Design%20Project%20Part%202.ng3", "Camera": {"Position": {"x": -19.032, "y": -81.955, "z": 92.922}, "Direction": {"x": 0.152, "y": 0.654, "z": -0.741}, "Mode": "Rotate"}},
{"Timestamp": "2020-10-28 15:06:10", "File": "Design%20Project%20Part%202.ng3", "Camera": {"Position": {"x": -57.938, "y": -99.298, "z": 49.964}, "Direction": {"x": 0.462, "y": 0.792, "z": -0.399}, "Mode": "Rotate"}},
{"Timestamp": "2020-10-28 15:06:19", "File": "Design%20Project%20Part%202.ng3", "Add Tree": {"Species": "Dogwood", "ID": 15, "Coordinates": [{"x": 0, "y": -58, "z": -0}]}},
{"Timestamp": "2020-10-28 15:06:21", "File": "Design%20Project%20Part%202.ng3", "Camera": {"Position": {"x": -6.315, "y": -118.624, "z": 40.024}, "Direction": {"x": 0.05, "y": 0.946, "z": -0.319}, "Mode": "Rotate"}},
{"Timestamp": "2020-10-28 15:06:29", "File": "Design%20Project%20Part%202.ng3", "Add Tree": {"Species": "Dogwood", "ID": 16, "Coordinates": [{"x": 15, "y": -56, "z": 0}]}},
{"Timestamp": "2020-10-28 15:06:33", "File": "Design%20Project%20Part%202.ng3", "Add Tree": {"Species": "Dogwood", "ID": 17, "Coordinates": [{"x": -15, "y": -55, "z": 0}]}},
{"Timestamp": "2020-10-28 15:06:36", "File": "Design%20Project%20Part%202.ng3", "Edit Tree": {"Species": "Dogwood", "ID": 17, "Coordinates": [{"x": -14.797, "y": -56.946, "z": 0}]}},
{"Timestamp": "2020-10-28 15:08:41", "File": "Design%20Project%20Part%202.ng3", "Graph Tab": "Energy"},
{"Timestamp": "2020-10-28 15:08:45", "File": "Design%20Project%20Part%202.ng3", "EnergyAnnualAnalysis": {"Months": 12, "Building": 2, "Net": {"Monthly": [54.87,45.12,31.7,19.88,45.52,44.82,51.94,52.78,38.91,29.84,43.03,55.98]
, "Total": 15646.53}, "AC": {"Monthly": [0,0,0,0,35.84,44.82,51.94,52.78,23.03,0,0,0]
, "Total": 6339.28}, "Heater": {"Monthly": [54.87,45.12,31.7,19.88,9.68,0,0,0,15.88,29.84,43.03,55.98]
, "Total": 9307.25}, "Windows": {"Monthly": [38.16,37.95,39.15,33.51,31.66,31.93,39.2,45.22,32.48,23.79,31.99,28.51]
, "Total": 12578.35}, "Solar Panels": {"Monthly": [0,0,0,0,0,0,0,0,0,0,0,0]
, "Total": 0}}},
{"Timestamp": "2020-10-28 15:11:40", "File": "Design%20Project%20Part%202.ng3", "Remove Tree": {"Species": "Dogwood", "ID": 15, "Coordinates": [{"x": 0, "y": -58, "z": -0}]}},
{"Timestamp": "2020-10-28 15:11:41", "File": "Design%20Project%20Part%202.ng3", "Remove Tree": {"Species": "Dogwood", "ID": 16, "Coordinates": [{"x": 15, "y": -56, "z": 0}]}},
{"Timestamp": "2020-10-28 15:11:42", "File": "Design%20Project%20Part%202.ng3", "Remove Tree": {"Species": "Dogwood", "ID": 17, "Coordinates": [{"x": -14.797, "y": -56.946, "z": 0}]}},
{"Timestamp": "2020-10-28 15:12:26", "File": "Design%20Project%20Part%202.ng3", "Edit Window": {"Type": "Window", "Building": 2, "ID": 10, "Coordinates": [{"x": 23, "y": -35, "z": 21}, {"x": 23, "y": -35, "z": 15}, {"x": 29, "y": -35, "z": 21}, {"x": 29, "y": -35, "z": 15}]}},
{"Timestamp": "2020-10-28 15:12:26", "File": "Design%20Project%20Part%202.ng3", "Camera": {"Position": {"x": -6.286, "y": -118.08, "z": 39.84}, "Direction": {"x": 0.05, "y": 0.946, "z": -0.319}, "Mode": "Zoom"}},
{"Timestamp": "2020-10-28 15:12:27", "File": "Design%20Project%20Part%202.ng3", "Camera": {"Position": {"x": -5.952, "y": -111.801, "z": 37.722}, "Direction": {"x": 0.05, "y": 0.946, "z": -0.319}, "Mode": "Zoom"}},
{"Timestamp": "2020-10-28 15:12:27", "File": "Design%20Project%20Part%202.ng3", "Camera": {"Position": {"x": -5.42, "y": -101.82, "z": 34.354}, "Direction": {"x": 0.05, "y": 0.946, "z": -0.319}, "Mode": "Zoom"}},
{"Timestamp": "2020-10-28 15:12:27", "File": "Design%20Project%20Part%202.ng3", "Camera": {"Position": {"x": -5.442, "y": -102.23, "z": 34.493}, "Direction": {"x": 0.05, "y": 0.946, "z": -0.319}, "Mode": "Zoom"}},
{"Timestamp": "2020-10-28 15:12:28", "File": "Design%20Project%20Part%202.ng3", "Camera": {"Position": {"x": -5.921, "y": -111.23, "z": 37.529}, "Direction": {"x": 0.05, "y": 0.946, "z": -0.319}, "Mode": "Zoom"}},
{"Timestamp": "2020-10-28 15:12:36", "File": "Design%20Project%20Part%202.ng3", "Graph Tab": "Cost"},
{"Timestamp": "2020-10-28 15:12:59", "File": "Design%20Project%20Part%202.ng3", "Graph Tab": "Energy"},
{"Timestamp": "2020-10-28 15:13:03", "File": "Design%20Project%20Part%202.ng3", "EnergyAnnualAnalysis": {"Months": 12, "Building": 2, "Net": {"Monthly": [51.31,42.46,27.74,15.55,18.57,15.54,15.25,11.64,17.14,22.94,38.62,51.42]
, "Total": 9982.07}, "AC": {"Monthly": [0,0,0,0,11.52,15.54,15.25,11.64,5.64,0,0,0]
, "Total": 1812.68}, "Heater": {"Monthly": [51.31,42.46,27.74,15.55,7.04,0,0,0,11.5,22.94,38.62,51.42]
, "Total": 8169.39}, "Windows": {"Monthly": [3,3.17,3.67,3.77,4.13,4.36,4.82,5.08,5,4.45,2.49,2.21]
, "Total": 1403.7}, "Solar Panels": {"Monthly": [0,0,0,0,0,0,0,0,0,0,0,0]
, "Total": 0}}},
{"Timestamp": "2020-10-28 15:13:39", "File": "Design%20Project%20Part%202.ng3", "Camera": {"Position": {"x": -7.102, "y": -90.648, "z": 75.809}, "Direction": {"x": 0.06, "y": 0.766, "z": -0.64}, "Mode": "Rotate"}},
{"Timestamp": "2020-10-28 15:14:35", "File": "Design%20Project%20Part%202.ng3", "Add Rack": {"Type": "Rack", "Building": 2, "ID": 18, "Coordinates": [{"x": 2.125, "y": -29.638, "z": 28.727}]}},
{"Timestamp": "2020-10-28 15:14:38", "File": "Design%20Project%20Part%202.ng3", "Edit Rack": {"Type": "Rack", "Building": 2, "ID": 18, "Coordinates": [{"x": -0.473, "y": -29.638, "z": 28.727}]}},
{"Timestamp": "2020-10-28 15:14:42", "File": "Design%20Project%20Part%202.ng3", "Edit Rack": {"Type": "Rack", "Building": 2, "ID": 18, "Coordinates": [{"x": 4.621, "y": -29.638, "z": 28.727}]}},
{"Timestamp": "2020-10-28 15:14:46", "File": "Design%20Project%20Part%202.ng3", "Edit Rack": {"Type": "Rack", "Building": 2, "ID": 18, "Coordinates": [{"x": 2.537, "y": -29.638, "z": 28.727}]}},
{"Timestamp": "2020-10-28 15:14:46", "File": "Design%20Project%20Part%202.ng3", "Camera": {"Position": {"x": -7.007, "y": -89.436, "z": 74.795}, "Direction": {"x": 0.06, "y": 0.766, "z": -0.64}, "Mode": "Zoom"}},
{"Timestamp": "2020-10-28 15:14:47", "File": "Design%20Project%20Part%202.ng3", "Camera": {"Position": {"x": -6.349, "y": -81.038, "z": 67.772}, "Direction": {"x": 0.06, "y": 0.766, "z": -0.64}, "Mode": "Zoom"}},
{"Timestamp": "2020-10-28 15:14:47", "File": "Design%20Project%20Part%202.ng3", "Camera": {"Position": {"x": -5.957, "y": -76.037, "z": 63.589}, "Direction": {"x": 0.06, "y": 0.766, "z": -0.64}, "Mode": "Zoom"}},
{"Timestamp": "2020-10-28 15:14:51", "File": "Design%20Project%20Part%202.ng3", "Add Rack": {"Type": "Rack", "Building": 2, "ID": 20, "Coordinates": [{"x": 2.537, "y": -21.388, "z": 31.782}]}},
{"Timestamp": "2020-10-28 15:14:54", "File": "Design%20Project%20Part%202.ng3", "Edit Rack": {"Type": "Rack", "Building": 2, "ID": 20, "Coordinates": [{"x": 0.091, "y": -21.388, "z": 31.782}]}},
{"Timestamp": "2020-10-28 15:14:58", "File": "Design%20Project%20Part%202.ng3", "Edit Rack": {"Type": "Rack", "Building": 2, "ID": 20, "Coordinates": [{"x": 2.537, "y": -21.8, "z": 31.63}]}},
{"Timestamp": "2020-10-28 15:14:59", "File": "Design%20Project%20Part%202.ng3", "Camera": {"Position": {"x": -5.896, "y": -75.261, "z": 62.941}, "Direction": {"x": 0.06, "y": 0.766, "z": -0.64}, "Mode": "Zoom"}},
{"Timestamp": "2020-10-28 15:15:00", "File": "Design%20Project%20Part%202.ng3", "Camera": {"Position": {"x": -5.36, "y": -68.422, "z": 57.221}, "Direction": {"x": 0.06, "y": 0.766, "z": -0.64}, "Mode": "Zoom"}},
{"Timestamp": "2020-10-28 15:15:00", "File": "Design%20Project%20Part%202.ng3", "Camera": {"Position": {"x": -5.437, "y": -69.402, "z": 58.04}, "Direction": {"x": 0.06, "y": 0.766, "z": -0.64}, "Mode": "Zoom"}},
{"Timestamp": "2020-10-28 15:15:01", "File": "Design%20Project%20Part%202.ng3", "Camera": {"Position": {"x": -6.318, "y": -81.619, "z": 68.258}, "Direction": {"x": 0.06, "y": 0.766, "z": -0.64}, "Mode": "Zoom"}},
{"Timestamp": "2020-10-28 15:15:01", "File": "Design%20Project%20Part%202.ng3", "Camera": {"Position": {"x": -6.743, "y": -86.069, "z": 71.979}, "Direction": {"x": 0.06, "y": 0.766, "z": -0.64}, "Mode": "Zoom"}},
{"Timestamp": "2020-10-28 15:15:01", "File": "Design%20Project%20Part%202.ng3", "Camera": {"Position": {"x": -7.362, "y": -93.972, "z": 78.588}, "Direction": {"x": 0.06, "y": 0.766, "z": -0.64}, "Mode": "Zoom"}},
{"Timestamp": "2020-10-28 15:15:04", "File": "Design%20Project%20Part%202.ng3", "Graph Tab": "Cost"},
{"Timestamp": "2020-10-28 15:15:30", "File": "Design%20Project%20Part%202.ng3", "Graph Tab": "Energy"},
{"Timestamp": "2020-10-28 15:15:34", "File": "Design%20Project%20Part%202.ng3", "EnergyAnnualAnalysis": {"Months": 12, "Building": 2, "Net": {"Monthly": [43.72,33.47,16.03,1.96,2.42,-1.3,-1.98,-4.53,3.27,11.85,32.66,46.09]
, "Total": 5585.98}, "AC": {"Monthly": [0,0,0,0,11.52,15.53,15.25,11.63,5.64,0,0,0]
, "Total": 1812.17}, "Heater": {"Monthly": [51.31,42.46,27.75,15.56,7.04,0,0,0,11.5,22.94,38.63,51.42]
, "Total": 8169.8}, "Windows": {"Monthly": [3,3.17,3.67,3.77,4.13,4.36,4.82,5.08,5,4.45,2.49,2.21]
, "Total": 1403.7}, "Solar Panels": {"Monthly": [7.59,8.99,11.72,13.6,16.14,16.83,17.23,16.16,13.87,11.09,5.97,5.33]
, "Total": 4395.99}}},
{"Timestamp": "2020-10-28 15:18:45", "File": "Design%20Project%20Part%202.ng3", "Graph Tab": "Cost"},
{"Timestamp": "2020-10-28 15:18:47", "File": "Design%20Project%20Part%202.ng3", "Camera": {"Position": {"x": -83.03, "y": -84.236, "z": 32.732}, "Direction": {"x": 0.677, "y": 0.686, "z": -0.267}, "Mode": "Rotate"}},
{"Timestamp": "2020-10-28 15:18:53", "File": "Design%20Project%20Part%202.ng3", "Edit Foundation": {"Type": "Foundation", "Building": 2, "ID": 2, "Coordinates": [{"x": -45, "y": -35, "z": 0}, {"x": -45, "y": 15, "z": 0}, {"x": 40, "y": -35, "z": 0}, {"x": 40, "y": 15, "z": 0}, {"x": -45, "y": -35, "z": 36}, {"x": -45, "y": 15, "z": 36}, {"x": 40, "y": -35, "z": 36}, {"x": 40, "y": 15, "z": 36}, {"x": 43, "y": -10, "z": 0}, {"x": -48, "y": -10, "z": 0}, {"x": -2.5, "y": 18, "z": 0}, {"x": -2.5, "y": -38, "z": 0}], "Height": 7, "Area": 150, "CenterX": 0.5, "CenterY": -2}},
{"Timestamp": "2020-10-28 15:18:55", "File": "Design%20Project%20Part%202.ng3", "Camera": {"Position": {"x": -82.099, "y": -83.292, "z": 32.365}, "Direction": {"x": 0.677, "y": 0.686, "z": -0.267}, "Mode": "Zoom"}},
{"Timestamp": "2020-10-28 15:18:56", "File": "Design%20Project%20Part%202.ng3", "Camera": {"Position": {"x": -72.903, "y": -73.963, "z": 28.74}, "Direction": {"x": 0.677, "y": 0.686, "z": -0.267}, "Mode": "Zoom"}},
{"Timestamp": "2020-10-28 15:18:56", "File": "Design%20Project%20Part%202.ng3", "Camera": {"Position": {"x": -71.219, "y": -71.658, "z": 27.844}, "Direction": {"x": 0.677, "y": 0.686, "z": -0.267}, "Mode": "Zoom"}},
{"Timestamp": "2020-10-28 15:18:56", "File": "Design%20Project%20Part%202.ng3", "Camera": {"Position": {"x": -68.661, "y": -69.659, "z": 27.067}, "Direction": {"x": 0.677, "y": 0.686, "z": -0.267}, "Mode": "Zoom"}},
{"Timestamp": "2020-10-28 15:18:56", "File": "Design%20Project%20Part%202.ng3", "Camera": {"Position": {"x": -58.511, "y": -59.361, "z": 23.066}, "Direction": {"x": 0.677, "y": 0.686, "z": -0.267}, "Mode": "Zoom"}},
{"Timestamp": "2020-10-28 15:18:59", "File": "Design%20Project%20Part%202.ng3", "Camera": {"Position": {"x": -78.926, "y": -37.409, "z": 12.752}, "Direction": {"x": 0.894, "y": 0.424, "z": -0.144}, "Mode": "Rotate"}},
{"Timestamp": "2020-10-28 15:18:59", "File": "Design%20Project%20Part%202.ng3", "Camera": {"Position": {"x": -80.339, "y": -38.079, "z": 12.981}, "Direction": {"x": 0.894, "y": 0.424, "z": -0.144}, "Mode": "Zoom"}},
{"Timestamp": "2020-10-28 15:19:00", "File": "Design%20Project%20Part%202.ng3", "Camera": {"Position": {"x": -86.366, "y": -40.935, "z": 13.954}, "Direction": {"x": 0.894, "y": 0.424, "z": -0.144}, "Mode": "Zoom"}},
{"Timestamp": "2020-10-28 15:19:01", "File": "Design%20Project%20Part%202.ng3", "Camera": {"Position": {"x": -70.644, "y": -65.497, "z": 23.573}, "Direction": {"x": 0.712, "y": 0.66, "z": -0.238}, "Mode": "Rotate"}},
{"Timestamp": "2020-10-28 15:19:05", "File": "Design%20Project%20Part%202.ng3", "Camera": {"Position": {"x": -78.713, "y": -56.505, "z": 21.157}, "Direction": {"x": 0.794, "y": 0.57, "z": -0.213}, "Mode": "Rotate"}},
{"Timestamp": "2020-10-28 15:19:07", "File": "Design%20Project%20Part%202.ng3", "Edit Wall": {"Type": "Wall", "Building": 2, "ID": 6, "Coordinates": [{"x": -35, "y": 15, "z": 1}, {"x": -35, "y": 15, "z": 26}, {"x": -45, "y": -35, "z": 1}, {"x": -45, "y": -35, "z": 26}]}},
{"Timestamp": "2020-10-28 15:19:09", "File": "Design%20Project%20Part%202.ng3", "Camera": {"Position": {"x": -94.712, "y": -20.446, "z": 21.157}, "Direction": {"x": 0.955, "y": 0.206, "z": -0.213}, "Mode": "Rotate"}},
{"Timestamp": "2020-10-28 15:19:09", "File": "Design%20Project%20Part%202.ng3", "Camera": {"Position": {"x": -94.815, "y": -20.468, "z": 20.672}, "Direction": {"x": 0.956, "y": 0.206, "z": -0.208}, "Mode": "Rotate"}},
{"Timestamp": "2020-10-28 15:19:13", "File": "Design%20Project%20Part%202.ng3", "Edit Wall": {"Type": "Wall", "Building": 2, "ID": 6, "Coordinates": [{"x": -45, "y": 15, "z": 1}, {"x": -45, "y": 15, "z": 26}, {"x": -45, "y": -35, "z": 1}, {"x": -45, "y": -35, "z": 26}]}},
{"Timestamp": "2020-10-28 15:19:14", "File": "Design%20Project%20Part%202.ng3", "Camera": {"Position": {"x": -43.463, "y": -83.856, "z": 30.253}, "Direction": {"x": 0.438, "y": 0.846, "z": -0.305}, "Mode": "Rotate"}},
{"Timestamp": "2020-10-28 15:19:25", "File": "Design%20Project%20Part%202.ng3", "Edit Wall": {"Type": "Wall", "Building": 2, "ID": 4, "Coordinates": [{"x": -45, "y": -35, "z": 1}, {"x": -45, "y": -35, "z": 26}, {"x": 40, "y": -35, "z": 1}, {"x": 40, "y": -35, "z": 26}]}},
{"Timestamp": "2020-10-28 15:19:26", "File": "Design%20Project%20Part%202.ng3", "Camera": {"Position": {"x": -79.843, "y": 56.089, "z": 17.754}, "Direction": {"x": 0.805, "y": -0.566, "z": -0.179}, "Mode": "Rotate"}},
{"Timestamp": "2020-10-28 15:19:29", "File": "Design%20Project%20Part%202.ng3", "Edit Wall": {"Type": "Wall", "Building": 2, "ID": 8, "Coordinates": [{"x": 40, "y": 15, "z": 1}, {"x": 40, "y": 15, "z": 26}, {"x": -45, "y": 15, "z": 1}, {"x": -45, "y": 15, "z": 26}]}},
{"Timestamp": "2020-10-28 15:19:29", "File": "Design%20Project%20Part%202.ng3", "Camera": {"Position": {"x": -79.562, "y": 56.487, "z": 17.754}, "Direction": {"x": 0.802, "y": -0.57, "z": -0.179}, "Mode": "Rotate"}},
{"Timestamp": "2020-10-28 15:19:30", "File": "Design%20Project%20Part%202.ng3", "Camera": {"Position": {"x": -21.708, "y": -87.497, "z": 41.342}, "Direction": {"x": 0.219, "y": 0.882, "z": -0.417}, "Mode": "Rotate"}},
{"Timestamp": "2020-10-28 15:19:30", "File": "Design%20Project%20Part%202.ng3", "Camera": {"Position": {"x": -22.174, "y": -89.375, "z": 42.23}, "Direction": {"x": 0.219, "y": 0.882, "z": -0.417}, "Mode": "Zoom"}},
{"Timestamp": "2020-10-28 15:19:30", "File": "Design%20Project%20Part%202.ng3", "Camera": {"Position": {"x": -25.285, "y": -101.915, "z": 48.155}, "Direction": {"x": 0.219, "y": 0.882, "z": -0.417}, "Mode": "Zoom"}},
{"Timestamp": "2020-10-28 15:19:31", "File": "Design%20Project%20Part%202.ng3", "Camera": {"Position": {"x": -26.422, "y": -107.193, "z": 50.649}, "Direction": {"x": 0.219, "y": 0.882, "z": -0.417}, "Mode": "Zoom"}},
{"Timestamp": "2020-10-28 15:19:33", "File": "Design%20Project%20Part%202.ng3", "Graph Tab": "Basics"},
{"Timestamp": "2020-10-28 15:20:00", "File": "Design%20Project%20Part%202.ng3", "Camera": {"Position": {"x": -26.081, "y": -105.124, "z": 49.671}, "Direction": {"x": 0.219, "y": 0.882, "z": -0.417}, "Mode": "Zoom"}},
{"Timestamp": "2020-10-28 15:20:00", "File": "Design%20Project%20Part%202.ng3", "Camera": {"Position": {"x": -24.884, "y": -100.302, "z": 47.392}, "Direction": {"x": 0.219, "y": 0.882, "z": -0.417}, "Mode": "Zoom"}},
{"Timestamp": "2020-10-28 15:20:06", "File": "Design%20Project%20Part%202.ng3", "Camera": {"Position": {"x": -12.394, "y": -80.274, "z": 79.55}, "Direction": {"x": 0.109, "y": 0.706, "z": -0.7}, "Mode": "Rotate"}},
{"Timestamp": "2020-10-28 15:20:10", "File": "Design%20Project%20Part%202.ng3", "Edit Rack": {"Type": "Rack", "Building": 2, "ID": 18, "Coordinates": [{"x": -0.075, "y": -29.638, "z": 28.727}]}},
{"Timestamp": "2020-10-28 15:20:16", "File": "Design%20Project%20Part%202.ng3", "Edit Rack": {"Type": "Rack", "Building": 2, "ID": 20, "Coordinates": [{"x": -0.035, "y": -21.8, "z": 31.63}]}},
{"Timestamp": "2020-10-28 15:20:19", "File": "Design%20Project%20Part%202.ng3", "Camera": {"Position": {"x": -4.845, "y": -70.953, "z": 88.701}, "Direction": {"x": 0.043, "y": 0.624, "z": -0.78}, "Mode": "Rotate"}},
{"Timestamp": "2020-10-28 15:20:25", "File": "Design%20Project%20Part%202.ng3", "Edit Rack": {"Type": "Rack", "Building": 2, "ID": 20, "Coordinates": [{"x": 1.2, "y": -22.212, "z": 31.477}]}},
{"Timestamp": "2020-10-28 15:20:25", "File": "Design%20Project%20Part%202.ng3", "Camera": {"Position": {"x": -4.815, "y": -70.509, "z": 89.056}, "Direction": {"x": 0.042, "y": 0.62, "z": -0.783}, "Mode": "Rotate"}},
{"Timestamp": "2020-10-28 15:20:26", "File": "Design%20Project%20Part%202.ng3", "Camera": {"Position": {"x": -4.705, "y": -68.901, "z": 87.025}, "Direction": {"x": 0.042, "y": 0.62, "z": -0.783}, "Mode": "Zoom"}},
{"Timestamp": "2020-10-28 15:20:26", "File": "Design%20Project%20Part%202.ng3", "Camera": {"Position": {"x": -3.917, "y": -57.36, "z": 72.448}, "Direction": {"x": 0.042, "y": 0.62, "z": -0.783}, "Mode": "Zoom"}},
{"Timestamp": "2020-10-28 15:20:27", "File": "Design%20Project%20Part%202.ng3", "Camera": {"Position": {"x": -3.391, "y": -49.651, "z": 62.711}, "Direction": {"x": 0.042, "y": 0.62, "z": -0.783}, "Mode": "Zoom"}},
{"Timestamp": "2020-10-28 15:20:28", "File": "Design%20Project%20Part%202.ng3", "Camera": {"Position": {"x": -3.434, "y": -50.28, "z": 63.506}, "Direction": {"x": 0.042, "y": 0.62, "z": -0.783}, "Mode": "Zoom"}},
{"Timestamp": "2020-10-28 15:20:28", "File": "Design%20Project%20Part%202.ng3", "Camera": {"Position": {"x": -3.874, "y": -56.73, "z": 71.652}, "Direction": {"x": 0.042, "y": 0.62, "z": -0.783}, "Mode": "Zoom"}},
{"Timestamp": "2020-10-28 15:20:29", "File": "Design%20Project%20Part%202.ng3", "Camera": {"Position": {"x": -25.544, "y": -80.244, "z": 52.794}, "Direction": {"x": 0.257, "y": 0.807, "z": -0.531}, "Mode": "Rotate"}},
{"Timestamp": "2020-10-28 15:20:30", "File": "Design%20Project%20Part%202.ng3", "Camera": {"Position": {"x": -26.051, "y": -81.837, "z": 53.842}, "Direction": {"x": 0.257, "y": 0.807, "z": -0.531}, "Mode": "Zoom"}},
{"Timestamp": "2020-10-28 15:20:30", "File": "Design%20Project%20Part%202.ng3", "Camera": {"Position": {"x": -29.571, "y": -92.894, "z": 61.117}, "Direction": {"x": 0.257, "y": 0.807, "z": -0.531}, "Mode": "Zoom"}},
{"Timestamp": "2020-10-28 15:20:30", "File": "Design%20Project%20Part%202.ng3", "Camera": {"Position": {"x": -31.394, "y": -98.623, "z": 64.886}, "Direction": {"x": 0.257, "y": 0.807, "z": -0.531}, "Mode": "Zoom"}},
{"Timestamp": "2020-10-28 15:20:34", "File": "Design%20Project%20Part%202.ng3", "Graph Tab": "Cost"},
{"Timestamp": "2020-10-28 15:20:37", "File": "Design%20Project%20Part%202.ng3", "Graph Tab": "Basics"},
{"Timestamp": "2020-10-28 15:21:14", "File": "Design%20Project%20Part%202.ng3", "Graph Tab": "Cost"},
{"Timestamp": "2020-10-28 15:21:28", "File": "Design%20Project%20Part%202.ng3", "Graph Tab": "Energy"},
{"Timestamp": "2020-10-28 15:21:32", "File": "Design%20Project%20Part%202.ng3", "EnergyAnnualAnalysis": {"Months": 12, "Building": 2, "Net": {"Monthly": [47.11,35.79,16.49,2,1.89,-2.24,-3.08,-5.83,2.82,12.1,35.16,49.91]
, "Total": 5844.23}, "AC": {"Monthly": [0,0,0,0.86,13.02,17.4,17.02,13.03,6.42,0,0,0]
, "Total": 2060.8}, "Heater": {"Monthly": [55.97,46.28,30.16,17.01,7.7,0,0,0,12.58,25.03,42.13,56.13]
, "Total": 8912.09}, "Windows": {"Monthly": [3.29,3.46,3.98,4.04,4.4,4.64,5.15,5.47,5.43,4.87,2.74,2.44]
, "Total": 1517.89}, "Solar Panels": {"Monthly": [8.86,10.49,13.67,15.87,18.83,19.64,20.1,18.86,16.18,12.94,6.96,6.22]
, "Total": 5128.65}}},
{"Timestamp": "2020-10-28 15:21:52", "File": "Design%20Project%20Part%202.ng3", "Undo": "Edit Rack"},
{"Timestamp": "2020-10-28 15:21:52", "File": "Design%20Project%20Part%202.ng3", "Undo": "Edit Rack"},
{"Timestamp": "2020-10-28 15:21:53", "File": "Design%20Project%20Part%202.ng3", "Undo": "Edit Rack"},
{"Timestamp": "2020-10-28 15:21:53", "File": "Design%20Project%20Part%202.ng3", "Undo": "Edit Wall"},
{"Timestamp": "2020-10-28 15:21:54", "File": "Design%20Project%20Part%202.ng3", "Undo": "Edit Wall"},
{"Timestamp": "2020-10-28 15:21:54", "File": "Design%20Project%20Part%202.ng3", "Undo": "Edit Wall"},
{"Timestamp": "2020-10-28 15:21:55", "File": "Design%20Project%20Part%202.ng3", "Undo": "Edit Wall"},
{"Timestamp": "2020-10-28 15:21:55", "File": "Design%20Project%20Part%202.ng3", "Undo": "Edit Foundation"},
{"Timestamp": "2020-10-28 15:22:15", "File": "Design%20Project%20Part%202.ng3", "Camera": {"Position": {"x": -35.804, "y": -112.474, "z": 73.999}, "Direction": {"x": 0.257, "y": 0.807, "z": -0.531}, "Mode": "Zoom"}},
{"Timestamp": "2020-10-28 15:22:15", "File": "Design%20Project%20Part%202.ng3", "Camera": {"Position": {"x": -33.452, "y": -103.657, "z": 68.198}, "Direction": {"x": 0.257, "y": 0.807, "z": -0.531}, "Mode": "Zoom"}},
{"Timestamp": "2020-10-28 15:22:15", "File": "Design%20Project%20Part%202.ng3", "Camera": {"Position": {"x": -31.827, "y": -99.981, "z": 65.779}, "Direction": {"x": 0.257, "y": 0.807, "z": -0.531}, "Mode": "Zoom"}},
{"Timestamp": "2020-10-28 15:22:17", "File": "Design%20Project%20Part%202.ng3", "Camera": {"Position": {"x": -53.514, "y": -88.634, "z": 65.632}, "Direction": {"x": 0.437, "y": 0.723, "z": -0.535}, "Mode": "Rotate"}},
{"Timestamp": "2020-10-28 15:22:18", "File": "Design%20Project%20Part%202.ng3", "Camera": {"Position": {"x": -54.167, "y": -89.714, "z": 66.432}, "Direction": {"x": 0.437, "y": 0.723, "z": -0.535}, "Mode": "Zoom"}},
{"Timestamp": "2020-10-28 15:22:27", "File": "Design%20Project%20Part%202.ng3", "EnergyAnnualAnalysis": {"Months": 12, "Building": 2, "Net": {"Monthly": [43.72,33.47,16.03,1.96,2.42,-1.3,-1.98,-4.53,3.27,11.85,32.66,46.09]
, "Total": 5585.98}, "AC": {"Monthly": [0,0,0,0,11.52,15.53,15.25,11.63,5.64,0,0,0]
, "Total": 1812.17}, "Heater": {"Monthly": [51.31,42.46,27.75,15.56,7.04,0,0,0,11.5,22.94,38.63,51.42]
, "Total": 8169.8}, "Windows": {"Monthly": [3,3.17,3.67,3.77,4.13,4.36,4.82,5.08,5,4.45,2.49,2.21]
, "Total": 1403.7}, "Solar Panels": {"Monthly": [7.59,8.99,11.72,13.6,16.14,16.83,17.23,16.16,13.87,11.09,5.97,5.33]
, "Total": 4395.99}}},
{"Timestamp": "2020-10-28 15:22:40", "File": "Design%20Project%20Part%202.ng3", "Camera": {"Position": {"x": -43.006, "y": -114.887, "z": 56.257}, "Direction": {"x": 0.319, "y": 0.851, "z": -0.417}, "Mode": "Rotate"}},
{"Timestamp": "2020-10-28 15:22:42", "File": "Design%20Project%20Part%202.ng3", "Graph Tab": "Basics"},
{"Timestamp": "2020-10-28 15:23:24", "File": "Design%20Project%20Part%202.ng3", "Edit PyramidRoof": {"Type": "PyramidRoof", "Building": 2, "ID": 9, "Coordinates": [{"x": 2.5, "y": -10, "z": 38.5}]}},
{"Timestamp": "2020-10-28 15:23:26", "File": "Design%20Project%20Part%202.ng3", "Edit PyramidRoof": {"Type": "PyramidRoof", "Building": 2, "ID": 9, "Coordinates": [{"x": 2.5, "y": -10, "z": 43.5}]}},
{"Timestamp": "2020-10-28 15:23:28", "File": "Design%20Project%20Part%202.ng3", "Edit PyramidRoof": {"Type": "PyramidRoof", "Building": 2, "ID": 9, "Coordinates": [{"x": 2.5, "y": -10, "z": 46}]}},
{"Timestamp": "2020-10-28 15:23:33", "File": "Design%20Project%20Part%202.ng3", "Graph Tab": "Cost"},
{"Timestamp": "2020-10-28 15:23:36", "File": "Design%20Project%20Part%202.ng3", "Camera": {"Position": {"x": -19.26, "y": -110.094, "z": 75.642}, "Direction": {"x": 0.143, "y": 0.816, "z": -0.56}, "Mode": "Rotate"}},
{"Timestamp": "2020-10-28 15:23:37", "File": "Design%20Project%20Part%202.ng3", "Camera": {"Position": {"x": -19.116, "y": -109.275, "z": 75.079}, "Direction": {"x": 0.143, "y": 0.816, "z": -0.56}, "Mode": "Zoom"}},
{"Timestamp": "2020-10-28 15:23:37", "File": "Design%20Project%20Part%202.ng3", "Camera": {"Position": {"x": -17.817, "y": -101.846, "z": 69.975}, "Direction": {"x": 0.143, "y": 0.816, "z": -0.56}, "Mode": "Zoom"}},
{"Timestamp": "2020-10-28 15:23:37", "File": "Design%20Project%20Part%202.ng3", "Camera": {"Position": {"x": -16.679, "y": -95.344, "z": 65.508}, "Direction": {"x": 0.143, "y": 0.816, "z": -0.56}, "Mode": "Zoom"}},
{"Timestamp": "2020-10-28 15:23:38", "File": "Design%20Project%20Part%202.ng3", "Edit Rack": {"Type": "Rack", "Building": 2, "ID": 18, "Coordinates": [{"x": 2.537, "y": -28.812, "z": 32.065}]}},
{"Timestamp": "2020-10-28 15:23:40", "File": "Design%20Project%20Part%202.ng3", "Edit Rack": {"Type": "Rack", "Building": 2, "ID": 18, "Coordinates": [{"x": 2.125, "y": -30.875, "z": 30.537}]}},
{"Timestamp": "2020-10-28 15:23:43", "File": "Design%20Project%20Part%202.ng3", "Edit Rack": {"Type": "Rack", "Building": 2, "ID": 18, "Coordinates": [{"x": -0.535, "y": -30.875, "z": 30.537}]}},
{"Timestamp": "2020-10-28 15:23:49", "File": "Design%20Project%20Part%202.ng3", "Edit Rack": {"Type": "Rack", "Building": 2, "ID": 18, "Coordinates": [{"x": 5.012, "y": -30.875, "z": 30.537}]}},
{"Timestamp": "2020-10-28 15:23:51", "File": "Design%20Project%20Part%202.ng3", "Camera": {"Position": {"x": -22.581, "y": -93.004, "z": 64.773}, "Direction": {"x": 0.195, "y": 0.805, "z": -0.56}, "Mode": "Rotate"}},
{"Timestamp": "2020-10-28 15:23:55", "File": "Design%20Project%20Part%202.ng3", "Edit Rack": {"Type": "Rack", "Building": 2, "ID": 18, "Coordinates": [{"x": 2.494, "y": -30.875, "z": 30.537}]}},
{"Timestamp": "2020-10-28 15:23:58", "File": "Design%20Project%20Part%202.ng3", "Camera": {"Position": {"x": -3.258, "y": -85.28, "z": 77.922}, "Direction": {"x": 0.028, "y": 0.738, "z": -0.674}, "Mode": "Rotate"}},
{"Timestamp": "2020-10-28 15:24:00", "File": "Design%20Project%20Part%202.ng3", "Edit Rack": {"Type": "Rack", "Building": 2, "ID": 20, "Coordinates": [{"x": 2.537, "y": -24.275, "z": 35.426}]}},
{"Timestamp": "2020-10-28 15:24:03", "File": "Design%20Project%20Part%202.ng3", "Edit Rack": {"Type": "Rack", "Building": 2, "ID": 20, "Coordinates": [{"x": 5.131, "y": -24.275, "z": 35.426}]}},
{"Timestamp": "2020-10-28 15:24:10", "File": "Design%20Project%20Part%202.ng3", "Edit Rack": {"Type": "Rack", "Building": 2, "ID": 20, "Coordinates": [{"x": 2.537, "y": -24.275, "z": 35.426}]}},
{"Timestamp": "2020-10-28 15:24:15", "File": "Design%20Project%20Part%202.ng3", "Add SolarPanel": {"Type": "SolarPanel", "Building": 2, "ID": 24, "Coordinates": [{"x": 2.62, "y": -17.675, "z": 40.315}]}},
{"Timestamp": "2020-10-28 15:24:18", "File": "Design%20Project%20Part%202.ng3", "Camera": {"Position": {"x": -3.296, "y": -86.274, "z": 78.83}, "Direction": {"x": 0.028, "y": 0.738, "z": -0.674}, "Mode": "Zoom"}},
{"Timestamp": "2020-10-28 15:24:19", "File": "Design%20Project%20Part%202.ng3", "Camera": {"Position": {"x": -3.803, "y": -99.536, "z": 90.948}, "Direction": {"x": 0.028, "y": 0.738, "z": -0.674}, "Mode": "Zoom"}},
{"Timestamp": "2020-10-28 15:24:21", "File": "Design%20Project%20Part%202.ng3", "Camera": {"Position": {"x": -56.592, "y": -122.365, "z": 34.421}, "Direction": {"x": 0.407, "y": 0.879, "z": -0.247}, "Mode": "Rotate"}},
{"Timestamp": "2020-10-28 15:24:23", "File": "Design%20Project%20Part%202.ng3", "Camera": {"Position": {"x": -55.979, "y": -122.646, "z": 34.421}, "Direction": {"x": 0.402, "y": 0.881, "z": -0.247}, "Mode": "Rotate"}},
{"Timestamp": "2020-10-28 15:24:38", "File": "Design%20Project%20Part%202.ng3", "Graph Tab": "Basics"},
{"Timestamp": "2020-10-28 15:24:50", "File": "Design%20Project%20Part%202.ng3", "Graph Tab": "Energy"},
{"Timestamp": "2020-10-28 15:24:55", "File": "Design%20Project%20Part%202.ng3", "EnergyAnnualAnalysis": {"Months": 12, "Building": 2, "Net": {"Monthly": [41.68,31.05,12.73,-1.01,-0.91,-4.67,-5.92,-9.48,-1.97,7.11,30.81,45.1]
, "Total": 4395.64}, "AC": {"Monthly": [0,0,0,0.42,11.85,16.09,15.86,12.07,5.82,0,0,0]
, "Total": 1889.41}, "Heater": {"Monthly": [53.67,44.44,29.05,16.27,7.36,0,0,0,12.02,24,40.39,53.76]
, "Total": 8545.93}, "Windows": {"Monthly": [3,3.17,3.67,3.77,4.12,4.36,4.82,5.08,5,4.45,2.49,2.21]
, "Total": 1403.47}, "Solar Panels": {"Monthly": [11.98,13.39,16.32,17.7,20.12,20.76,21.78,21.56,19.81,16.9,9.58,8.66]
, "Total": 6039.7}}},
{"Timestamp": "2020-10-28 15:26:23", "File": "Design%20Project%20Part%202.ng3", "Camera": {"Position": {"x": -55.502, "y": -121.602, "z": 34.128}, "Direction": {"x": 0.402, "y": 0.881, "z": -0.247}, "Mode": "Zoom"}},
{"Timestamp": "2020-10-28 15:26:24", "File": "Design%20Project%20Part%202.ng3", "Camera": {"Position": {"x": -35.362, "y": -103.854, "z": 80.83}, "Direction": {"x": 0.259, "y": 0.762, "z": -0.593}, "Mode": "Rotate"}},
{"Timestamp": "2020-10-28 15:26:25", "File": "Design%20Project%20Part%202.ng3", "Remove PyramidRoof": {"Type": "PyramidRoof", "Building": 2, "ID": 9, "Coordinates": [{"x": 2.5, "y": -10, "z": 46}]}},
{"Timestamp": "2020-10-28 15:26:28", "File": "Design%20Project%20Part%202.ng3", "Add HipRoof": {"Type": "HipRoof", "Building": 2, "ID": 26, "Coordinates": [{"x": 2.5, "y": -10, "z": 41}, {"x": 22.25, "y": -10, "z": 41}, {"x": -17.25, "y": -10, "z": 41}]}},
{"Timestamp": "2020-10-28 15:26:30", "File": "Design%20Project%20Part%202.ng3", "Camera": {"Position": {"x": -10.833, "y": -109.98, "z": 79.729}, "Direction": {"x": 0.079, "y": 0.807, "z": -0.585}, "Mode": "Rotate"}},
{"Timestamp": "2020-10-28 15:26:30", "File": "Design%20Project%20Part%202.ng3", "Camera": {"Position": {"x": -10.733, "y": -108.958, "z": 78.988}, "Direction": {"x": 0.079, "y": 0.807, "z": -0.585}, "Mode": "Zoom"}},
{"Timestamp": "2020-10-28 15:26:30", "File": "Design%20Project%20Part%202.ng3", "Camera": {"Position": {"x": -10.015, "y": -101.669, "z": 73.704}, "Direction": {"x": 0.079, "y": 0.807, "z": -0.585}, "Mode": "Zoom"}},
{"Timestamp": "2020-10-28 15:26:30", "File": "Design%20Project%20Part%202.ng3", "Camera": {"Position": {"x": -9.716, "y": -98.633, "z": 71.503}, "Direction": {"x": 0.079, "y": 0.807, "z": -0.585}, "Mode": "Zoom"}},
{"Timestamp": "2020-10-28 15:26:55", "File": "Design%20Project%20Part%202.ng3", "Camera": {"Position": {"x": -9.546, "y": -96.911, "z": 70.255}, "Direction": {"x": 0.079, "y": 0.807, "z": -0.585}, "Mode": "Zoom"}},
{"Timestamp": "2020-10-28 15:26:55", "File": "Design%20Project%20Part%202.ng3", "Camera": {"Position": {"x": -8.928, "y": -90.641, "z": 65.709}, "Direction": {"x": 0.079, "y": 0.807, "z": -0.585}, "Mode": "Zoom"}},
{"Timestamp": "2020-10-28 15:26:56", "File": "Design%20Project%20Part%202.ng3", "Camera": {"Position": {"x": -8.76, "y": -88.931, "z": 64.47}, "Direction": {"x": 0.079, "y": 0.807, "z": -0.585}, "Mode": "Zoom"}},
{"Timestamp": "2020-10-28 15:26:56", "File": "Design%20Project%20Part%202.ng3", "Camera": {"Position": {"x": -9.325, "y": -94.668, "z": 68.629}, "Direction": {"x": 0.079, "y": 0.807, "z": -0.585}, "Mode": "Zoom"}},
{"Timestamp": "2020-10-28 15:26:58", "File": "Design%20Project%20Part%202.ng3", "Camera": {"Position": {"x": -26.599, "y": -80.756, "z": 80.808}, "Direction": {"x": 0.227, "y": 0.688, "z": -0.689}, "Mode": "Rotate"}},
{"Timestamp": "2020-10-28 15:27:15", "File": "Design%20Project%20Part%202.ng3", "Camera": {"Position": {"x": -27.087, "y": -82.237, "z": 82.289}, "Direction": {"x": 0.227, "y": 0.688, "z": -0.689}, "Mode": "Zoom"}},
{"Timestamp": "2020-10-28 15:27:16", "File": "Design%20Project%20Part%202.ng3", "Camera": {"Position": {"x": -27.047, "y": -82.116, "z": 82.168}, "Direction": {"x": 0.227, "y": 0.688, "z": -0.689}, "Mode": "Zoom"}},
{"Timestamp": "2020-10-28 15:27:18", "File": "Design%20Project%20Part%202.ng3", "Camera": {"Position": {"x": -10.987, "y": -92.533, "z": 66.521}, "Direction": {"x": 0.096, "y": 0.808, "z": -0.581}, "Mode": "Rotate"}},
{"Timestamp": "2020-10-28 15:27:24", "File": "Design%20Project%20Part%202.ng3", "Add Rack": {"Type": "Rack", "Building": 2, "ID": 28, "Coordinates": [{"x": -14.788, "y": -30.463, "z": 29.632}]}},
{"Timestamp": "2020-10-28 15:27:30", "File": "Design%20Project%20Part%202.ng3", "Edit Rack": {"Type": "Rack", "Building": 2, "ID": 28, "Coordinates": [{"x": 2.635, "y": -30.463, "z": 29.632}]}},
{"Timestamp": "2020-10-28 15:27:31", "File": "Design%20Project%20Part%202.ng3", "Camera": {"Position": {"x": -11.026, "y": -92.862, "z": 66.054}, "Direction": {"x": 0.096, "y": 0.811, "z": -0.577}, "Mode": "Rotate"}},
{"Timestamp": "2020-10-28 15:27:35", "File": "Design%20Project%20Part%202.ng3", "Add Rack": {"Type": "Rack", "Building": 2, "ID": 30, "Coordinates": [{"x": -10.25, "y": -23.038, "z": 33.757}]}},
{"Timestamp": "2020-10-28 15:27:39", "File": "Design%20Project%20Part%202.ng3", "Edit Rack": {"Type": "Rack", "Building": 2, "ID": 30, "Coordinates": [{"x": 2.244, "y": -23.038, "z": 33.757}]}},
{"Timestamp": "2020-10-28 15:27:42", "File": "Design%20Project%20Part%202.ng3", "Add Rack": {"Type": "Rack", "Building": 2, "ID": 32, "Coordinates": [{"x": -2.825, "y": -15.613, "z": 37.882}]}},
{"Timestamp": "2020-10-28 15:27:47", "File": "Design%20Project%20Part%202.ng3", "Edit Rack": {"Type": "Rack", "Building": 2, "ID": 32, "Coordinates": [{"x": 2.257, "y": -15.613, "z": 37.882}]}},
{"Timestamp": "2020-10-28 15:27:48", "File": "Design%20Project%20Part%202.ng3", "Graph Tab": "Cost"},
{"Timestamp": "2020-10-28 15:28:04", "File": "Design%20Project%20Part%202.ng3", "Graph Tab": "Basics"},
{"Timestamp": "2020-10-28 15:28:32", "File": "Design%20Project%20Part%202.ng3", "Graph Tab": "Cost"},
{"Timestamp": "2020-10-28 15:28:42", "File": "Design%20Project%20Part%202.ng3", "Graph Tab": "Energy"},
{"Timestamp": "2020-10-28 15:28:47", "File": "Design%20Project%20Part%202.ng3", "EnergyAnnualAnalysis": {"Months": 12, "Building": 2, "Net": {"Monthly": [33.24,21.01,-0.38,-15.44,-18.28,-22.76,-24.45,-26.91,-16.77,-5.13,24.18,39.17]
, "Total": -381.08}, "AC": {"Monthly": [0,0,0,1.01,12.22,16.49,16.26,12.41,6.26,0,0,0]
, "Total": 1966.65}, "Heater": {"Monthly": [53.55,44.28,28.82,16.21,7.35,0,0,0,12.02,23.94,40.31,53.67]
, "Total": 8521.36}, "Windows": {"Monthly": [3,3.17,3.67,3.77,4.13,4.36,4.82,5.08,5,4.45,2.49,2.21]
, "Total": 1403.77}, "Solar Panels": {"Monthly": [20.32,23.26,29.2,32.66,37.86,39.26,40.71,39.32,35.05,29.07,16.13,14.51]
, "Total": 10869.09}}},
{"Timestamp": "2020-10-28 15:29:12", "File": "Design%20Project%20Part%202.ng3", "Camera": {"Position": {"x": -11.121, "y": -93.661, "z": 66.623}, "Direction": {"x": 0.096, "y": 0.811, "z": -0.577}, "Mode": "Zoom"}},
{"Timestamp": "2020-10-28 15:29:12", "File": "Design%20Project%20Part%202.ng3", "Camera": {"Position": {"x": -12.583, "y": -105.972, "z": 75.38}, "Direction": {"x": 0.096, "y": 0.811, "z": -0.577}, "Mode": "Zoom"}},
{"Timestamp": "2020-10-28 15:29:14", "File": "Design%20Project%20Part%202.ng3", "Camera": {"Position": {"x": -23.571, "y": -123.77, "z": 42.45}, "Direction": {"x": 0.177, "y": 0.931, "z": -0.319}, "Mode": "Rotate"}},
{"Timestamp": "2020-10-28 15:29:16", "File": "Design%20Project%20Part%202.ng3", "Graph Tab": "Basics"},
{"Timestamp": "2020-10-28 15:30:18", "File": "Design%20Project%20Part%202.ng3", "Camera": {"Position": {"x": 20.29, "y": -120.502, "z": 52.383}, "Direction": {"x": -0.153, "y": 0.906, "z": -0.394}, "Mode": "Rotate"}},
{"Timestamp": "2020-10-28 15:30:23", "File": "Design%20Project%20Part%202.ng3", "Camera": {"Position": {"x": -23.684, "y": -117.936, "z": 56.627}, "Direction": {"x": 0.178, "y": 0.887, "z": -0.426}, "Mode": "Rotate"}}]}