{
"Activities": [
{"Timestamp": "2020-10-21 15:54:20", "File": "Energy%20Small%20Design%20Exercise.ng3", "Show Annotation": false},
{"Timestamp": "2020-10-21 16:08:32", "File": "Energy%20Small%20Design%20Exercise.ng3", "Camera": {"Position": {"x": 90.506, "y": -64.174, "z": 94.403}, "Direction": {"x": -0.621, "y": 0.44, "z": -0.648}, "Mode": "Rotate"}},
{"Timestamp": "2020-10-21 16:08:34", "File": "Energy%20Small%20Design%20Exercise.ng3", "Edit Window": {"Type": "Window", "Building": 2, "ID": 17, "Coordinates": [{"x": 40, "y": -16, "z": 25}, {"x": 40, "y": -16, "z": 15}, {"x": 40, "y": -8, "z": 25}, {"x": 40, "y": -8, "z": 15}]}},
{"Timestamp": "2020-10-21 16:08:37", "File": "Energy%20Small%20Design%20Exercise.ng3", "Camera": {"Position": {"x": 93.022, "y": -21.974, "z": 109.915}, "Direction": {"x": -0.638, "y": 0.151, "z": -0.755}, "Mode": "Rotate"}},
{"Timestamp": "2020-10-21 16:08:39", "File": "Energy%20Small%20Design%20Exercise.ng3", "Remove Rack": {"Type": "Rack", "Building": 2, "ID": 43, "Coordinates": [{"x": 21.875, "y": 0.368, "z": 42.979}]}},
{"Timestamp": "2020-10-21 16:08:40", "File": "Energy%20Small%20Design%20Exercise.ng3", "Remove Rack": {"Type": "Rack", "Building": 2, "ID": 38, "Coordinates": [{"x": 29.3, "y": 0.139, "z": 38.56}]}},
{"Timestamp": "2020-10-21 16:08:41", "File": "Energy%20Small%20Design%20Exercise.ng3", "Remove Rack": {"Type": "Rack", "Building": 2, "ID": 34, "Coordinates": [{"x": 36.312, "y": -12.63, "z": 34.385}]}},
{"Timestamp": "2020-10-21 16:08:42", "File": "Energy%20Small%20Design%20Exercise.ng3", "Remove Rack": {"Type": "Rack", "Building": 2, "ID": 36, "Coordinates": [{"x": 36.312, "y": 12.075, "z": 34.385}]}},
{"Timestamp": "2020-10-21 16:08:55", "File": "Energy%20Small%20Design%20Exercise.ng3", "Camera": {"Position": {"x": -72.341, "y": -113.974, "z": 54.722}, "Direction": {"x": 0.497, "y": 0.782, "z": -0.376}, "Mode": "Rotate"}},
{"Timestamp": "2020-10-21 16:08:58", "File": "Energy%20Small%20Design%20Exercise.ng3", "Camera": {"Position": {"x": -59.575, "y": -103.925, "z": 82.859}, "Direction": {"x": 0.409, "y": 0.713, "z": -0.569}, "Mode": "Rotate"}},
{"Timestamp": "2020-10-21 16:09:02", "File": "Energy%20Small%20Design%20Exercise.ng3", "Remove Rack": {"Type": "Rack", "Building": 2, "ID": 29, "Coordinates": [{"x": -0.414, "y": -11.919, "z": 46.689}]}},
{"Timestamp": "2020-10-21 16:09:04", "File": "Energy%20Small%20Design%20Exercise.ng3", "Remove Rack": {"Type": "Rack", "Building": 2, "ID": 27, "Coordinates": [{"x": -0.101, "y": -19.371, "z": 40.867}]}},
{"Timestamp": "2020-10-21 16:09:05", "File": "Energy%20Small%20Design%20Exercise.ng3", "Remove Rack": {"Type": "Rack", "Building": 2, "ID": 23, "Coordinates": [{"x": -15.327, "y": -26.288, "z": 35.463}]}},
{"Timestamp": "2020-10-21 16:09:06", "File": "Energy%20Small%20Design%20Exercise.ng3", "Remove Rack": {"Type": "Rack", "Building": 2, "ID": 25, "Coordinates": [{"x": 14.928, "y": -26.288, "z": 35.463}]}},
{"Timestamp": "2020-10-21 16:09:09", "File": "Energy%20Small%20Design%20Exercise.ng3", "Camera": {"Position": {"x": -18.234, "y": -124.351, "z": 73.652}, "Direction": {"x": 0.125, "y": 0.853, "z": -0.506}, "Mode": "Rotate"}},
{"Timestamp": "2020-10-21 16:09:45", "File": "Energy%20Small%20Design%20Exercise.ng3", "Camera": {"Position": {"x": 73.047, "y": -87.765, "z": 90.464}, "Direction": {"x": -0.501, "y": 0.602, "z": -0.621}, "Mode": "Rotate"}},
{"Timestamp": "2020-10-21 16:09:49", "File": "Energy%20Small%20Design%20Exercise.ng3", "Camera": {"Position": {"x": -31.87, "y": -124.51, "z": 68.568}, "Direction": {"x": 0.219, "y": 0.854, "z": -0.471}, "Mode": "Rotate"}},
{"Timestamp": "2020-10-21 16:09:50", "File": "Energy%20Small%20Design%20Exercise.ng3", "Graph Tab": "Energy"},
{"Timestamp": "2020-10-21 16:09:54", "File": "Energy%20Small%20Design%20Exercise.ng3", "Graph Tab": "Cost"},
{"Timestamp": "2020-10-21 16:10:06", "File": "Energy%20Small%20Design%20Exercise.ng3", "BuildingDailyEnergyGraph": {"Building": 2, "Net": {"Hourly": [0.42828,0.3846,0.55955,0.92863,1.42021,2.00079,3.47934,8.46484,11.5209,13.30355,14.29631,14.55683,15.13567,17.10123,17.83542,17.14254,14.22299,6.688,2.82138,2.18489,1.58527,1.06341,0.67642,0.52054]
, "Total": 168.32}, "AC": {"Hourly": [0.42828,0.3846,0.55955,0.92863,1.42021,2.00079,3.47934,8.46484,11.5209,13.30355,14.29631,14.55683,15.13567,17.10123,17.83542,17.14254,14.22299,6.688,2.82138,2.18489,1.58527,1.06341,0.67642,0.52054]
, "Total": 168.32}, "Heater": {"Hourly": [0,0,0,0,0,0,0,0,0,0,0,0,0,0,0,0,0,0,0,0,0,0,0,0]
, "Total": 0}, "Windows": {"Hourly": [0,0,0,0,0,0,0.72752,4.46362,6.57559,7.66798,8.1858,8.20639,8.70255,10.73501,11.76855,11.61996,9.45607,3.0185,0,0,0,0,0,0]
, "Total": 91.13}, "Solar Panels": {"Hourly": [0,0,0,0,0,0,0,0,0,0,0,0,0,0,0,0,0,0,0,0,0,0,0,0]
, "Total": 0}}, "Solar Potential": [{"Building": 2, "Daily": 2644.37}]},
{"Timestamp": "2020-10-21 16:10:34", "File": "Energy%20Small%20Design%20Exercise.ng3", "Camera": {"Position": {"x": 51.067, "y": 111.444, "z": 78.617}, "Direction": {"x": -0.35, "y": -0.765, "z": -0.54}, "Mode": "Rotate"}},
{"Timestamp": "2020-10-21 16:10:35", "File": "Energy%20Small%20Design%20Exercise.ng3", "Camera": {"Position": {"x": -109.826, "y": 70.399, "z": 64.683}, "Direction": {"x": 0.754, "y": -0.484, "z": -0.444}, "Mode": "Rotate"}},
{"Timestamp": "2020-10-21 16:10:39", "File": "Energy%20Small%20Design%20Exercise.ng3", "Camera": {"Position": {"x": -82.941, "y": -75.024, "z": 93.289}, "Direction": {"x": 0.57, "y": 0.515, "z": -0.641}, "Mode": "Rotate"}},
{"Timestamp": "2020-10-21 16:10:43", "File": "Energy%20Small%20Design%20Exercise.ng3", "Graph Tab": "Cost"},
{"Timestamp": "2020-10-21 16:10:45", "File": "Energy%20Small%20Design%20Exercise.ng3", "Graph Tab": "Energy"},
{"Timestamp": "2020-10-21 16:11:50", "File": "Energy%20Small%20Design%20Exercise.ng3", "EnergyDailyAnalysis": {"Building": 2, "Net": {"Hourly": [0.42828,0.3846,0.55955,0.92863,1.42021,2.00079,3.47934,8.46484,11.5209,13.30355,14.29631,14.55683,15.13567,17.10123,17.83542,17.14254,14.22299,6.688,2.82138,2.18489,1.58527,1.06341,0.67642,0.52054]
, "Total": 168.32}, "AC": {"Hourly": [0.42828,0.3846,0.55955,0.92863,1.42021,2.00079,3.47934,8.46484,11.5209,13.30355,14.29631,14.55683,15.13567,17.10123,17.83542,17.14254,14.22299,6.688,2.82138,2.18489,1.58527,1.06341,0.67642,0.52054]
, "Total": 168.32}, "Heater": {"Hourly": [0,0,0,0,0,0,0,0,0,0,0,0,0,0,0,0,0,0,0,0,0,0,0,0]
, "Total": 0}, "Windows": {"Hourly": [0,0,0,0,0,0,0.72752,4.46362,6.57559,7.66798,8.1858,8.20639,8.70255,10.73501,11.76855,11.61996,9.45607,3.0185,0,0,0,0,0,0]
, "Total": 91.13}, "Solar Panels": {"Hourly": [0,0,0,0,0,0,0,0,0,0,0,0,0,0,0,0,0,0,0,0,0,0,0,0]
, "Total": 0}}},
{"Timestamp": "2020-10-21 16:20:54", "File": "Energy%20Small%20Design%20Exercise.ng3", "Graph Tab": "Cost"},
{"Timestamp": "2020-10-21 16:20:57", "File": "Energy%20Small%20Design%20Exercise.ng3", "Camera": {"Position": {"x": -83.949, "y": -75.935, "z": 94.423}, "Direction": {"x": 0.57, "y": 0.515, "z": -0.641}, "Mode": "Zoom"}},
{"Timestamp": "2020-10-21 16:20:57", "File": "Energy%20Small%20Design%20Exercise.ng3", "Camera": {"Position": {"x": -88.168, "y": -79.748, "z": 99.169}, "Direction": {"x": 0.57, "y": 0.515, "z": -0.641}, "Mode": "Zoom"}},
{"Timestamp": "2020-10-21 16:20:57", "File": "Energy%20Small%20Design%20Exercise.ng3", "Camera": {"Position": {"x": -85.921, "y": -77.718, "z": 96.642}, "Direction": {"x": 0.57, "y": 0.515, "z": -0.641}, "Mode": "Zoom"}},
{"Timestamp": "2020-10-21 16:20:58", "File": "Energy%20Small%20Design%20Exercise.ng3", "Camera": {"Position": {"x": -81.271, "y": -73.515, "z": 91.411}, "Direction": {"x": 0.57, "y": 0.515, "z": -0.641}, "Mode": "Zoom"}},
{"Timestamp": "2020-10-21 16:20:58", "File": "Energy%20Small%20Design%20Exercise.ng3", "Camera": {"Position": {"x": -77.389, "y": -70.007, "z": 87.045}, "Direction": {"x": 0.57, "y": 0.515, "z": -0.641}, "Mode": "Zoom"}},
{"Timestamp": "2020-10-21 16:21:30", "File": "Energy%20Small%20Design%20Exercise.ng3", "Camera": {"Position": {"x": -78.219, "y": -70.757, "z": 87.978}, "Direction": {"x": 0.57, "y": 0.515, "z": -0.641}, "Mode": "Zoom"}},
{"Timestamp": "2020-10-21 16:21:30", "File": "Energy%20Small%20Design%20Exercise.ng3", "Camera": {"Position": {"x": -89.928, "y": -81.339, "z": 101.149}, "Direction": {"x": 0.57, "y": 0.515, "z": -0.641}, "Mode": "Zoom"}},
{"Timestamp": "2020-10-21 16:21:30", "File": "Energy%20Small%20Design%20Exercise.ng3", "Camera": {"Position": {"x": -94.991, "y": -85.915, "z": 106.845}, "Direction": {"x": 0.57, "y": 0.515, "z": -0.641}, "Mode": "Zoom"}},
{"Timestamp": "2020-10-21 16:21:31", "File": "Energy%20Small%20Design%20Exercise.ng3", "Camera": {"Position": {"x": -85.461, "y": -77.302, "z": 96.124}, "Direction": {"x": 0.57, "y": 0.515, "z": -0.641}, "Mode": "Zoom"}},
{"Timestamp": "2020-10-21 16:21:31", "File": "Energy%20Small%20Design%20Exercise.ng3", "Camera": {"Position": {"x": -79.684, "y": -68.605, "z": 85.299}, "Direction": {"x": 0.57, "y": 0.515, "z": -0.641}, "Mode": "Zoom"}},
{"Timestamp": "2020-10-21 16:21:31", "File": "Energy%20Small%20Design%20Exercise.ng3", "Camera": {"Position": {"x": -75.838, "y": -68.605, "z": 85.299}, "Direction": {"x": 0.57, "y": 0.515, "z": -0.641}, "Mode": "Zoom"}},
{"Timestamp": "2020-10-21 16:21:32", "File": "Energy%20Small%20Design%20Exercise.ng3", "Camera": {"Position": {"x": -75.641, "y": -68.427, "z": 85.078}, "Direction": {"x": 0.57, "y": 0.515, "z": -0.641}, "Mode": "Zoom"}},
{"Timestamp": "2020-10-21 16:21:32", "File": "Energy%20Small%20Design%20Exercise.ng3", "Camera": {"Position": {"x": -80.153, "y": -72.504, "z": 90.153}, "Direction": {"x": 0.57, "y": 0.515, "z": -0.641}, "Mode": "Zoom"}},{"Event String":"SO_P_P_PP_FP_P_P_P_PPPP_PPP_A_O_PPP_A"}]
}